{
  "88534": {
    "Luxembourg": 0,
    "Howald": 0,
    "Bettembourg": 0,
    "Thionville": 15,
    "Uckange": 15,
    "Hagondange": 15,
    "Metz": 20,
    "Pagny-sur-Moselle": 20,
    "Pont-à-Mousson": 20,
    "Nancy": 20
  },
  "88768": {
    "Metz": 30,
    "Metz Nord": 30,
    "Woippy": 30,
    "Maizières-lès-Metz": 30,
    "Hagondange": 30,
    "Uckange": 30,
    "Thionville": 30,
    "Hettange-Grande": 30,
    "Bettembourg": 30,
    "Luxembourg": 30
  },
  "88763": {
    "Luxembourg": 15,
    "Bettembourg": 15,
    "Hettange-Grande": 15,
    "Thionville": 15,
    "Uckange": 15,
    "Hagondange": 15,
    "Maizières-lès-Metz": 15,
    "Woippy": 15,
    "Metz Nord": 15,
    "Metz": 15
  },
  "88767": {
    "Luxembourg": 45,
    "Bettembourg": 40,
    "Hettange-Grande": 40,
    "Thionville": 40,
    "Uckange": 40,
    "Hagondange": 40,
    "Maizières-lès-Metz": 40,
    "Woippy": 40,
    "Metz Nord": 40,
    "Metz": 40
  },
  "88772": {
    "Metz": 15,
    "Hagondange": 20,
    "Uckange": 20,
    "Thionville": 20,
    "Bettembourg": 20,
    "Howald": 20,
    "Luxembourg": 20
  },
  "88769": {
    "Luxembourg": 10,
    "Howald": 10,
    "Bettembourg": 20,
    "Hettange-Grande": 20,
    "Thionville": 20,
    "Uckange": 20,
    "Hagondange": 20,
    "Metz": 20
  },
  "88774": {
    "Metz": 15,
    "Metz Nord": 12,
    "Woippy": 11,
    "Maizières-lès-Metz": 10,
    "Hagondange": 10,
    "Uckange": 10,
    "Thionville": 10,
    "Hettange-Grande": 10,
    "Bettembourg": 10,
    "Luxembourg": 10
  },
  "88771": {
    "Luxembourg": 0,
    "Howald": 0,
    "Bettembourg": 0,
    "Thionville": 0,
    "Uckange": 0,
    "Hagondange": 0,
    "Metz": 0
  },
  "88773": {
    "Luxembourg": 5,
    "Bettembourg": 5,
    "Hettange-Grande": 5,
    "Thionville": 5,
    "Uckange": 5,
    "Hagondange": 5,
    "Maizières-lès-Metz": 5,
    "Woippy": 5,
    "Metz Nord": 5,
    "Metz": 5
  },
  "88776": {
    "Metz": 0,
    "Hagondange": 0,
    "Uckange": 0,
    "Thionville": 0,
    "Bettembourg": 0,
    "Howald": 0,
    "Luxembourg": 0
  },
  "88778": {
    "Metz": 0,
    "Metz Nord": 0,
    "Woippy": 0,
    "Maizières-lès-Metz": 0,
    "Hagondange": 0,
    "Uckange": 0,
    "Thionville": 0,
    "Hettange-Grande": 0,
    "Bettembourg": 0,
    "Luxembourg": 0
  },
  "88777": {
    "Luxembourg": 0,
    "Bettembourg": 0,
    "Hettange-Grande": 0,
    "Thionville": 0,
    "Uckange": 0,
    "Hagondange": 0,
    "Maizières-lès-Metz": 0,
    "Woippy": 0,
    "Metz Nord": 0,
    "Metz": 0
  }
}