[
  {
    "situation_number": "QOM:Broadcast::5053080406696237778:LOC",
    "summary": "860719 : train supprimé",
    "description": "Le train 860719 est supprimé.\n\nPrendre le train 860745 départ de la gare de Tours à 19h07.",
    "severity": "slight",
    "affects": [
      {
        "vehicle_journeys": [
          "860719"
        ]
      }
    ]
  },
  {
    "situation_number": "QOM:Broadcast::8134891076589359134:LOC",
    "summary": "Voiture 6 dédiée au placement libre",
    "description": "Voiture 6 dédiée au placement libre",
    "severity": "slight",
    "affects": [
      {
        "vehicle_journeys": [
          "839580"
        ]
      }
    ]
  },
  {
    "situation_number": "QOM:Broadcast::6740708453040350992:LOC",
    "summary": "Achtung, einige nicht bediente Bahnhöfe",
    "description": "In RAON L'ETAPEhat sich ein Unfall mit Personenschaden ereignet.\n\nInfolgedessen bedient Ihr Zug einige Bahnhöfe nicht.",
    "severity": "slight",
    "affects": [
      {
        "vehicle_journeys": [
          "2596"
        ]
      }
    ]
  },
  {
    "situation_number": "QOM:Broadcast::2519592849902307326:LOC",
    "summary": "855369 : modification desserte",
    "description": "TER 855369 limité à Callac. Prise en charge taxi",
    "severity": "slight",
    "affects": [
      {
        "vehicle_journeys": [
          "855369"
        ]
      }
    ]
  },
  {
    "situation_number": "QOM:Broadcast::2744120303152011068:LOC",
    "summary": "Voiture 6 dédiée au placement libre",
    "description": "Voiture 6 dédiée au placement libre",
    "severity": "slight",
    "affects": [
      {
        "vehicle_journeys": [
          "839584"
        ]
      }
    ]
  },
  {
    "situation_number": "QOM:Broadcast::8109808516742631361:LOC",
    "summary": "TER 865206 du 17/06/25   : arrêt supplémentaire",
    "description": "Le TER 865206 du 17/06/25 fera un arrêt supplémentaire en gare de  : Razac.\n\nRendez-vous sur votre site TER Nouvelle-Aquitaine, sur SNCF Connect ou toute autre application de mobilité.",
    "severity": "slight",
    "affects": [
      {
        "vehicle_journeys": [
          "865206"
        ]
      }
    ]
  },
  {
    "situation_number": "QOM:Broadcast::5729449115668560121:LOC",
    "summary": "Ihr Zug hat Verspätung.",
    "description": "Ihr Zug hat Verspätung.\n\nGrund: Verzögerung eines Zuges, der vor Ihrem Zug in MANNHEIM verkehrt.",
    "severity": "slight",
    "affects": [
      {
        "vehicle_journeys": [
          "9550"
        ]
      }
    ]
  },
  {
    "situation_number": "QOM:Broadcast::949940658686628948:LOC",
    "summary": "Der Wagen nicht am Bahnsteig in den Bahnhöfen Courville-sur-Eure und Epernon.",
    "description": "Dieser Zug kann in den Bahnhöfen Courville-sur-Eure und Epernon über den Bahnsteig hinausragende Türen aufweisen. Reisende, die in diesen Bahnhöfen aussteigen, werden gebeten, sich zum vorderen Teil des Zuges zu begeben.",
    "severity": "slight",
    "affects": [
      {
        "vehicle_journeys": [
          "862508"
        ]
      }
    ]
  },
  {
    "situation_number": "QOM:Broadcast::2037752742750337648:LOC",
    "summary": "Informationen",
    "description": "Dieser Zug wird vom 30. Juni bis zum 14. August nicht verkehren, da das Angebot während der Sommermonate ausgedünnt wird.",
    "severity": "slight",
    "affects": [
      {
        "vehicle_journeys": [
          "832784",
          "832793",
          "96119",
          "96118",
          "831418",
          "831419",
          "831530",
          "831414",
          "96124",
          "96107",
          "96106",
          "832759",
          "832755",
          "832756",
          "830450",
          "832750",
          "832751",
          "96114",
          "832752",
          "96113",
          "96101",
          "832765",
          "96100",
          "832763",
          "831564",
          "830405",
          "830401",
          "831506",
          "831507",
          "830418",
          "830413",
          "831501",
          "830412",
          "830411",
          "830410",
          "830427",
          "96142",
          "830423",
          "96147",
          "96146",
          "831528",
          "831407",
          "830438",
          "831527",
          "830437",
          "831404",
          "831408",
          "831529",
          "830430",
          "96131",
          "831403",
          "830434"
        ]
      }
    ]
  },
  {
    "situation_number": "QOM:Broadcast::6148853919532742002:LOC",
    "summary": " Paris - Orléans : Panne d'un système d'aiguillage",
    "description": " Paris - Orléans : Panne d'un système d'aiguillage. Fin d'incident, reprise normale des circulations sur votre ligne.",
    "severity": "slight",
    "affects": [
      {
        "vehicle_journeys": [
          "860562",
          "860595",
          "860594",
          "860531",
          "860563",
          "860591",
          "860590",
          "860593",
          "860592",
          "860526",
          "860525",
          "860536",
          "860527",
          "860533",
          "860565",
          "860532",
          "860529"
        ]
      }
    ]
  },
  {
    "situation_number": "QOM:Broadcast::8779496637929105396:LOC",
    "summary": "853622 retardé",
    "description": "Votre train 853622 à destination de Le Mans doit circuler à vitesse réduite entre . Le mauvais fonctionnement d'un passage à niveau perturbe la circulation des trains près de Argentan.",
    "severity": "slight",
    "affects": [
      {
        "vehicle_journeys": [
          "853622"
        ]
      }
    ]
  },
  {
    "situation_number": "QOM:Broadcast::6636570360805474021:LOC",
    "summary": "Ihr Zug hat Verspätung.",
    "description": " \n\nUrsache: Die Schranken eines Bahnübergangs müssen in ST PIERRE DES CORPS überprüft werden.",
    "severity": "slight",
    "affects": [
      {
        "vehicle_journeys": [
          "5486",
          "5351"
        ]
      }
    ]
  },
  {
    "situation_number": "QOM:Broadcast::928426965343059204:LOC",
    "summary": "Verkehr gestört",
    "description": "Der Verkehr ist gestört. Unsere Teams sind im Einsatz.\n\nUrsache: Signalstörung zwischen CAZÈRES-SUR-GARONNE und TOULOUSE-MATABIAU.",
    "severity": "slight",
    "affects": [
      {
        "vehicle_journeys": [
          "14148"
        ]
      }
    ]
  },
  {
    "situation_number": "QOM:Broadcast::4225113944416321320:LOC",
    "summary": "Der Zug gelöscht",
    "description": "Ihr Zug wird gelöscht.\n\nGrund: Die Lokomotive Ihres Zuges ist in BORDEAUX liegen geblieben.",
    "severity": "slight",
    "affects": [
      {
        "vehicle_journeys": [
          "4665"
        ]
      }
    ]
  },
  {
    "situation_number": "QOM:Broadcast::298745302584814777:LOC",
    "summary": "Aufgrund zusätzlicher Wartungsarbeiten müssen wir die normale Route des Zuges ändern.",
    "description": "Aufgrund zusätzlicher Wartungsarbeiten müssen wir die normale Route des Zuges ändern.",
    "severity": "slight",
    "affects": [
      {
        "vehicle_journeys": [
          "86380"
        ]
      }
    ]
  },
  {
    "situation_number": "QOM:Broadcast::1143462983953095977:LOC",
    "summary": "Voiture 6 dédiée au placement libre",
    "description": "Voiture 6 dédiée au placement libre",
    "severity": "slight",
    "affects": [
      {
        "vehicle_journeys": [
          "839403"
        ]
      }
    ]
  },
  {
    "situation_number": "QOM:Broadcast::932121400964779471:LOC",
    "summary": "Ihr Zug hat Verspätung.",
    "description": "Ihr Zug hat Verspätung.\n\nGrund: Ein Zug, der vor Ihrem Zug in CHENAY GAGNY verkehrt, hat sich verlangsamt.",
    "severity": "slight",
    "affects": [
      {
        "vehicle_journeys": [
          "2719"
        ]
      }
    ]
  },
  {
    "situation_number": "QOM:Broadcast::6212122134851205397:LOC",
    "summary": "Voiture 6 dédiée au placement libre",
    "description": "Voiture 6 dédiée au placement libre",
    "severity": "slight",
    "affects": [
      {
        "vehicle_journeys": [
          "839582"
        ]
      }
    ]
  },
  {
    "situation_number": "QOM:Broadcast::7631944918521886838:LOC",
    "summary": "Train court.",
    "description": " \n\nVotre train sera un train court. Nous faisons tout pour rétablir cette situation.",
    "severity": "slight",
    "affects": [
      {
        "vehicle_journeys": [
          "23117"
        ]
      }
    ]
  },
  {
    "situation_number": "QOM:Broadcast::3561597917091335973:LOC",
    "summary": "Ihr Zug hat Verspätung.",
    "description": "Ihr Zug hat Verspätung. \n\nGrund: Technische Überprüfungen am Triebzug in FRANKFURT .",
    "severity": "slight",
    "affects": [
      {
        "vehicle_journeys": [
          "9580"
        ]
      }
    ]
  },
  {
    "situation_number": "QOM:Broadcast::5134457782086467088:LOC",
    "summary": "Ihr Zug hat Verspätung.",
    "description": "Ihr Zug hat eine Verspätung.\n\nGrund: Ein Zug, der vor Ihrem Zug in LUXEMBURG verkehrt, hat die Fahrt verlangsamt.",
    "severity": "slight",
    "affects": [
      {
        "vehicle_journeys": [
          "2807"
        ]
      }
    ]
  },
  {
    "situation_number": "QOM:Broadcast::1886431877046839391:LOC",
    "summary": "Ihr Zug hat Verspätung.",
    "description": "Ihr Zug hat eine Verspätung.\n\nGrund: Die Schranken eines Bahnübergangs müssen in BORDEAUX  überprüft werden.",
    "severity": "slight",
    "affects": [
      {
        "vehicle_journeys": [
          "3833",
          "3856"
        ]
      }
    ]
  },
  {
    "situation_number": "QOM:Broadcast::3916251744073779900:LOC",
    "summary": "Ihr Zug hat Verspätung.",
    "description": "Ihr Zug hat eine Verspätung.\n\nGrund: Reparaturarbeiten an Ihrem Zug in MULHOUSE.",
    "severity": "slight",
    "affects": [
      {
        "vehicle_journeys": [
          "5516",
          "2242"
        ]
      }
    ]
  },
  {
    "situation_number": "QOM:Broadcast::8629880508703375141:LOC",
    "summary": "Voiture 2 dédiée au placement libre",
    "description": "Voiture 2 dédiée au placement libre",
    "severity": "slight",
    "affects": [
      {
        "vehicle_journeys": [
          "839171"
        ]
      }
    ]
  },
  {
    "situation_number": "QOM:Broadcast::7783996048286375216:LOC",
    "summary": "Voiture 6 dédiée au placement libre",
    "description": "Voiture 6 dédiée au placement libre",
    "severity": "slight",
    "affects": [
      {
        "vehicle_journeys": [
          "839133"
        ]
      }
    ]
  },
  {
    "situation_number": "QOM:Broadcast::6672818462970765651:LOC",
    "summary": "Voiture 6 dédiée au placement libre",
    "description": "Voiture 6 dédiée au placement libre",
    "severity": "slight",
    "affects": [
      {
        "vehicle_journeys": [
          "839153"
        ]
      }
    ]
  },
  {
    "situation_number": "QOM:Broadcast::2368827705638059443:LOC",
    "summary": "Aufgrund zusätzlicher Wartungsarbeiten müssen wir die normale Route des Zuges ändern.",
    "description": "Aufgrund zusätzlicher Wartungsarbeiten müssen wir die normale Route des Zuges ändern.",
    "severity": "slight",
    "affects": [
      {
        "vehicle_journeys": [
          "86383"
        ]
      }
    ]
  },
  {
    "situation_number": "QOM:Broadcast::1229550360279420486:LOC",
    "summary": "17.06 REDUZIERTE ANZAHL SITZPLÄTZE",
    "description": "Der Zug wird voraussichtlich stark frequentiert sein, da die Anzahl der Sitzplätze reduziert wurde.\n\nWir bitten Sie, sich auf den gesamten Zug zu verteilen.",
    "severity": "slight",
    "affects": [
      {
        "vehicle_journeys": [
          "830516",
          "832904",
          "830625",
          "832905",
          "830612",
          "830619",
          "830618",
          "830573",
          "830566",
          "830543"
        ]
      }
    ]
  },
  {
    "situation_number": "QOM:Broadcast::6314401941455109353:LOC",
    "summary": "Aufgrund zusätzlicher Wartungsarbeiten müssen wir die normale Route des Zuges ändern.",
    "description": "Aufgrund zusätzlicher Wartungsarbeiten müssen wir die normale Route des Zuges ändern.",
    "severity": "slight",
    "affects": [
      {
        "vehicle_journeys": [
          "86381"
        ]
      }
    ]
  },
  {
    "situation_number": "QOM:Broadcast::5319597558749677561:LOC",
    "summary": "Voiture 6 dédiée au placement libre",
    "description": "Voiture 6 dédiée au placement libre",
    "severity": "slight",
    "affects": [
      {
        "vehicle_journeys": [
          "839141"
        ]
      }
    ]
  },
  {
    "situation_number": "QOM:Broadcast::1590449466625382384:LOC",
    "summary": "Reprise de la circulation en gare de Périgueux",
    "description": "La circulation reprend quasi normalement sur les lignes à destination et en provenance de Périgueux.\n\nMotif : présence d'un bagage délaissé à bord d'un train.\n\nDes retards restent à prévoir. Restez informés via vos outils d'information habituels.",
    "severity": "slight",
    "affects": [
      {}
    ]
  },
  {
    "situation_number": "QOM:Broadcast::6330650048325790125:LOC",
    "summary": "Der Zug wurde aufgrund der Verspätung auf einer früheren Fahrt erst spät bereitgestellt.",
    "description": "Der Zug wurde aufgrund der Verspätung auf einer früheren Fahrt erst spät bereitgestellt.",
    "severity": "slight",
    "affects": [
      {
        "vehicle_journeys": [
          "886948"
        ]
      }
    ]
  },
  {
    "situation_number": "QOM:Broadcast::4479228009845258959:LOC",
    "summary": "Der für die Abfahrt des Zuges erforderliche Zugbegleiter war nicht anwesend und konnte nicht ersetzt werden.",
    "description": "Der für die Abfahrt des Zuges erforderliche Zugbegleiter war nicht anwesend und konnte nicht ersetzt werden.",
    "severity": "slight",
    "affects": [
      {
        "vehicle_journeys": [
          "887361"
        ]
      }
    ]
  },
  {
    "situation_number": "QOM:Broadcast::4247209334388733997:LOC",
    "summary": "AFFLUENCE3",
    "description": "Ce train circule aujourd'hui avec un nombre réduit de places.",
    "severity": "slight",
    "affects": [
      {
        "vehicle_journeys": [
          "844902",
          "842472",
          "842408",
          "844917",
          "848908"
        ]
      }
    ]
  },
  {
    "situation_number": "QOM:Broadcast::236265744001499344:LOC",
    "summary": "",
    "description": "",
    "severity": "slight",
    "affects": [
      {}
    ]
  },
  {
    "situation_number": "QOM:Broadcast::7115028825057383617:LOC",
    "summary": "Ihr Zug hat Verspätung.",
    "description": "Ihr Zug hat Verspätung.\n\nGrund: Derzeit werden in LILLE EUROPE technische Überprüfungen an für den Betrieb Ihres Zuges wichtigen Organen durchgeführt.",
    "severity": "slight",
    "affects": [
      {
        "vehicle_journeys": [
          "9868",
          "9864"
        ]
      }
    ]
  },
  {
    "situation_number": "QOM:Broadcast::2593924953751959648:LOC",
    "summary": "Ihr Zug hat Verspätung.",
    "description": "Ihr Zug hat Verspätung.\n\nGrund: Reparaturen an Ihrem Zug in FRANKFURT .",
    "severity": "slight",
    "affects": [
      {
        "vehicle_journeys": [
          "9590"
        ]
      }
    ]
  },
  {
    "situation_number": "QOM:Broadcast::4175003367843265704:LOC",
    "summary": "Voiture 6 dédiée au placement libre",
    "description": "Voiture 6 dédiée au placement libre",
    "severity": "slight",
    "affects": [
      {
        "vehicle_journeys": [
          "839563"
        ]
      }
    ]
  },
  {
    "situation_number": "QOM:Broadcast::3443915322195736760:LOC",
    "summary": "Voitures 6, 11, 12 et 16 dédiées au placement libre",
    "description": "Voitures 6, 11, 12 et 16 dédiées au placement libre",
    "severity": "slight",
    "affects": [
      {
        "vehicle_journeys": [
          "839411"
        ]
      }
    ]
  },
  {
    "situation_number": "QOM:Broadcast::697798478445195144:LOC",
    "summary": "Les Aubrais: Bahnhof geschlossen und/oder DBR HS",
    "description": "Les Aubrais (Die Aubrais)\n\nVerkauf nur gegen In bar im Bahnhof möglich.",
    "severity": "slight",
    "affects": [
      {
        "stop_points": [
          "87543017"
        ]
      }
    ]
  },
  {
    "situation_number": "QOM:Broadcast::5357675382298191465:LOC",
    "summary": "Voiture 6 dédiée au placement libre",
    "description": "Voiture 6 dédiée au placement libre",
    "severity": "slight",
    "affects": [
      {
        "vehicle_journeys": [
          "839561"
        ]
      }
    ]
  },
  {
    "situation_number": "QOM:Broadcast::6146416921348240139:LOC",
    "summary": "Starker Zulauf",
    "description": "",
    "severity": "slight",
    "affects": [
      {
        "vehicle_journeys": [
          "854392"
        ]
      }
    ]
  },
  {
    "situation_number": "QOM:Broadcast::4473648824181058880:LOC",
    "summary": "Montdidier : guichet fermé",
    "description": "Montdidier : le guichet de la gare est fermé à la vente aujourd'hui lundi 16 juin. Votre titre de transport est disponible à l'achat en avance sur le site TER Hauts de France ou sur vos canaux de distribution habituels.",
    "severity": "slight",
    "affects": [
      {
        "vehicle_journeys": [
          "848447",
          "848458",
          "848457",
          "848438",
          "45809",
          "848443",
          "848442",
          "848453",
          "848464",
          "45806",
          "848444",
          "45804",
          "848450",
          "45802",
          "848452",
          "848451"
        ]
      }
    ]
  },
  {
    "situation_number": "QOM:Broadcast::8497606493628451925:LOC",
    "summary": "Le trafic reprend progressivement depuis .",
    "description": "Le trafic reprend progressivement depuis .\n\nQuelques retards sont encore à prévoir.\n\nCause : établissement d'un périmètre de sécurité retardant la circulation des trains à MONTAUBAN VILLE.",
    "severity": "slight",
    "affects": [
      {
        "vehicle_journeys": [
          "4752"
        ]
      }
    ]
  },
  {
    "situation_number": "QOM:Broadcast::8706825986204268676:LOC",
    "summary": "Travaux 28 et 29 juin",
    "description": "Importants travaux et interruption des circulations du samedi 28 juin 12h au dimanche 29 juin 12h entre Bordeaux et Langon dans les 2 sens. Plus d'infos sur le site TER Nouvelle Aquitaine.",
    "severity": "slight",
    "affects": [
      {}
    ]
  },
  {
    "situation_number": "QOM:Broadcast::803840636098596456:LOC",
    "summary": "AFFLUENCE3",
    "description": "Der Zug verkehrt heute mit einer geringeren Anzahl an Sitzplätzen.",
    "severity": "slight",
    "affects": [
      {
        "vehicle_journeys": [
          "847879",
          "847804",
          "847925",
          "847608",
          "848540"
        ]
      }
    ]
  },
  {
    "situation_number": "QOM:Broadcast::1944830039863352539:LOC",
    "summary": "Ihr Zug hat Verspätung.",
    "description": "Ihr Zug hat Verspätung.\n\nGrund: Ein Zug, der vor Ihrem Zug in LOURDES verkehrt, hat sich verlangsamt.",
    "severity": "slight",
    "affects": [
      {
        "vehicle_journeys": [
          "14143"
        ]
      }
    ]
  },
  {
    "situation_number": "QOM:Broadcast::7301534410826061527:LOC",
    "summary": "Voiture 6 dédiée au placement libre",
    "description": "Voiture 6 dédiée au placement libre",
    "severity": "slight",
    "affects": [
      {
        "vehicle_journeys": [
          "839553"
        ]
      }
    ]
  },
  {
    "situation_number": "QOM:Broadcast::8564196034749385383:LOC",
    "summary": "Travaux 28 et 29 juin",
    "description": "Importants travaux et interruption des circulations du samedi 28 juin 12h au dimanche 29 juin 12h entre Bordeaux et Langon dans les 2 sens. Plus d'infos sur le site TER Nouvelle Aquitaine.",
    "severity": "slight",
    "affects": [
      {
        "vehicle_journeys": [
          "453746",
          "453721",
          "453712",
          "866747",
          "866860",
          "866740",
          "866741",
          "866742",
          "866743",
          "866864",
          "866744",
          "866865",
          "866867",
          "866746",
          "866870",
          "866879",
          "453711",
          "866871",
          "866872",
          "866874",
          "866876",
          "866877",
          "866878",
          "866725",
          "866726",
          "866728",
          "866729",
          "866720",
          "866721",
          "866723",
          "866724",
          "866736",
          "866737",
          "866739",
          "71701",
          "71702",
          "866730",
          "866731",
          "866733",
          "866734",
          "866735",
          "866703",
          "866704",
          "866705",
          "866706",
          "866707",
          "866708",
          "866709",
          "866700",
          "866701",
          "866702",
          "866714",
          "866715",
          "866716",
          "866717",
          "866718",
          "866719",
          "866710",
          "866711",
          "866712",
          "866713"
        ]
      }
    ]
  },
  {
    "situation_number": "QOM:Broadcast::5944145129420420425:LOC",
    "summary": "Réduction du nombre de places assises.",
    "description": "839563 de Paris-Est 15h12 à Culmont-C roule avec un nombre de places réduit.\n\nLes clients des voitures 1 à 6 gardent leur réservation. Ceux des voitures 11 à 16 peuvent monter dans les voitures 1 à 6.",
    "severity": "slight",
    "affects": [
      {
        "vehicle_journeys": [
          "839563"
        ]
      }
    ]
  },
  {
    "situation_number": "QOM:Broadcast::1487625091326340480:LOC",
    "summary": "Verkehr gestört",
    "description": "Der Verkehr ist gestört. Unsere Teams sind im Einsatz.\n\nUrsache: Signalstörung in RENNES.",
    "severity": "slight",
    "affects": [
      {
        "vehicle_journeys": [
          "5210"
        ]
      }
    ]
  },
  {
    "situation_number": "QOM:Broadcast::2314026512285939355:LOC",
    "summary": "Geplante Arbeiten auf Ihrer Linie",
    "description": "Geplante Arbeiten auf Ihrer Linie",
    "severity": "slight",
    "affects": [
      {
        "vehicle_journeys": [
          "843924",
          "843925",
          "843923",
          "843928",
          "843926",
          "848936",
          "843920",
          "843008",
          "843921",
          "843914",
          "843911",
          "843912",
          "843917",
          "843918",
          "843915",
          "843916",
          "848920",
          "848922",
          "843919",
          "46562",
          "843942",
          "843943",
          "843940",
          "843941",
          "843935",
          "843936",
          "843933",
          "843934",
          "843939",
          "843937",
          "848946",
          "843931",
          "848942",
          "843932",
          "843930",
          "843903",
          "843900",
          "843901",
          "843906",
          "843904",
          "843905",
          "30725",
          "843908",
          "843909"
        ]
      }
    ]
  },
  {
    "situation_number": "QOM:Broadcast::1312037254318047670:LOC",
    "summary": "Voiture 2 dédiée au placement libre",
    "description": "Voiture 2 dédiée au placement libre",
    "severity": "slight",
    "affects": [
      {
        "vehicle_journeys": [
          "839161"
        ]
      }
    ]
  },
  {
    "situation_number": "QOM:Broadcast::6196794527409970092:LOC",
    "summary": "Ihr Zug hat Verspätung.",
    "description": "Ihr Zug hat eine Verspätung.\n\nGrund: Änderung der Zusammensetzung Ihres Zuges aufgrund eines technischen Problems in PARIS EST.",
    "severity": "slight",
    "affects": [
      {
        "vehicle_journeys": [
          "2067",
          "9577"
        ]
      }
    ]
  },
  {
    "situation_number": "QOM:Broadcast::4153593378876004272:LOC",
    "summary": "Travaux prévus entre Calais Ville et Boulogne.",
    "description": "Travaux prévus",
    "severity": "slight",
    "affects": [
      {
        "vehicle_journeys": [
          "848800"
        ]
      }
    ]
  },
  {
    "situation_number": "QOM:Broadcast::1249441153993819719:LOC",
    "summary": "Der Zug verspätet sich.",
    "description": "Der Verkehr wird seit 16.15 Uhr nach Intervention unserer spezialisierten Teams allmählich wieder aufgenommen.\n\nUrsache: Ein Weichensystem erforderte Überprüfungen am Eingang von ROUEN.",
    "severity": "slight",
    "affects": [
      {
        "vehicle_journeys": [
          "5316"
        ]
      }
    ]
  },
  {
    "situation_number": "QOM:Broadcast::3048822200682259738:LOC",
    "summary": "Templeuve",
    "description": "Templeuve : le guichet de la gare est fermé à la vente aujourd'hui lundi 16 juin. Votre titre de transport est disponible à l'achat en avance sur le site TER Hauts de France ou sur vos canaux de distribution habituels.",
    "severity": "slight",
    "affects": [
      {
        "vehicle_journeys": [
          "43406",
          "841228",
          "841822",
          "43405",
          "841227",
          "841821",
          "841824",
          "43407",
          "841229",
          "841823",
          "841826",
          "841825",
          "43404",
          "43403",
          "841827",
          "841222",
          "841221",
          "841224",
          "841223",
          "841226",
          "841820",
          "841225",
          "841271",
          "439068",
          "841811",
          "841813",
          "841812",
          "841815",
          "841814",
          "841817",
          "841816",
          "841253",
          "841252",
          "841254",
          "439113",
          "439112",
          "841819",
          "841818",
          "841921",
          "841920",
          "841249",
          "841923",
          "841922",
          "841925",
          "841924",
          "841242",
          "841241",
          "841244",
          "841243",
          "841246",
          "841245",
          "841248",
          "841247",
          "439121",
          "841251",
          "841250",
          "841809",
          "841239",
          "841238",
          "841912",
          "841911",
          "841914",
          "841913",
          "841916",
          "841915",
          "841231",
          "841230",
          "841233",
          "841232",
          "841235",
          "841234",
          "841237",
          "841236",
          "841240",
          "841918",
          "841917",
          "841919"
        ]
      }
    ]
  },
  {
    "situation_number": "QOM:Broadcast::130780363087829040:LOC",
    "summary": "Aus Sicherheitsgründen wird der Zugverkehr verlangsamt.",
    "description": "Aus Sicherheitsgründen wird der Zugverkehr verlangsamt.",
    "severity": "slight",
    "affects": [
      {
        "vehicle_journeys": [
          "96241"
        ]
      }
    ]
  },
  {
    "situation_number": "QOM:Broadcast::1245263917837425570:LOC",
    "summary": "Une panne sur le train entraîne sa suppression.",
    "description": "Une panne sur le train entraîne sa suppression.",
    "severity": "slight",
    "affects": [
      {
        "vehicle_journeys": [
          "841502"
        ]
      }
    ]
  },
  {
    "situation_number": "QOM:Broadcast::4090839489457406195:LOC",
    "summary": " Paris - Orléans : Panne d'un système d'aiguillage",
    "description": " Paris - Orléans : Panne d'un système d'aiguillage. Fin d'incident, reprise normale des circulations sur votre ligne.",
    "severity": "slight",
    "affects": [
      {}
    ]
  },
  {
    "situation_number": "QOM:Broadcast::5643722591329966319:LOC",
    "summary": "Ihr Zug hat Verspätung.",
    "description": "Ihr Zug hat eine Verspätung.\n\nGrund: Ein Zug, der in KARLSRUHE vor Ihrem Zug fährt, hat sich verlangsamt.",
    "severity": "slight",
    "affects": [
      {
        "vehicle_journeys": [
          "9570"
        ]
      }
    ]
  },
  {
    "situation_number": "QOM:Broadcast::1655802330574386688:LOC",
    "summary": "Voiture 6 dédiée au placement libre",
    "description": "Voiture 6 dédiée au placement libre",
    "severity": "slight",
    "affects": [
      {
        "vehicle_journeys": [
          "839409"
        ]
      }
    ]
  },
  {
    "situation_number": "QOM:Broadcast::4737688301431704986:LOC",
    "summary": "    16.06, Ecommoy, Hindernis auf dem Gleis",
    "description": "Verkehrsbehinderungen in Richtung Le Mans - Château-du-Loir auf der Strecke Tours - Le Mans - Alençon, Alençon - Le Mans - Tours bis zum Ende des Dienstes...\n\nHindernis auf dem Gleis in Ecommoy.\n\nUnsere technischen Teams sind im Einsatz.",
    "severity": "slight",
    "affects": [
      {
        "vehicle_journeys": [
          "857028",
          "857040",
          "857016"
        ]
      }
    ]
  },
  {
    "situation_number": "QOM:Broadcast::7648048055306759114:LOC",
    "summary": "Wagen nicht am Bahnsteig in den Bahnhöfen Courville-sur-Eure und Le Theil - La Rouge",
    "description": "Dieser Zug kann in den Bahnhöfen Courville-sur-Eure und Le Theil - La Rouge über den Bahnsteig hinausragende Türen aufweisen. Reisende, die in diesen Bahnhöfen aussteigen, werden gebeten, sich zum vorderen Teil des Zuges zu begeben.",
    "severity": "slight",
    "affects": [
      {
        "vehicle_journeys": [
          "862531"
        ]
      }
    ]
  },
  {
    "situation_number": "QOM:Broadcast::7658321272908471651:LOC",
    "summary": "Le train a été mis à disposition tardivement à la suite du retard sur un trajet précédent.",
    "description": "Le train a été mis à disposition tardivement à la suite du retard sur un trajet précédent.",
    "severity": "slight",
    "affects": [
      {
        "vehicle_journeys": [
          "843928"
        ]
      }
    ]
  },
  {
    "situation_number": "QOM:Broadcast::4893702329053708564:LOC",
    "summary": " : Votre TER du 17/06 sera supprimé.",
    "description": " : Votre TER du 17/06 sera supprimé.\n\nDes solutions plus adaptées à votre voyage peuvent être disponibles. Pour cela, rendez-vous sur votre site TER Nouvelle-Aquitaine, sur SNCF Connect ou toute autre application de mobilité.",
    "severity": "slight",
    "affects": [
      {
        "vehicle_journeys": [
          "865305"
        ]
      }
    ]
  },
  {
    "situation_number": "QOM:Broadcast::1930247737311444985:LOC",
    "summary": "Voiture 6 dédiée au placement libre",
    "description": "Voiture 6 dédiée au placement libre",
    "severity": "slight",
    "affects": [
      {
        "vehicle_journeys": [
          "839129"
        ]
      }
    ]
  },
  {
    "situation_number": "QOM:Broadcast::8805311198187597660:LOC",
    "summary": "Ihr Zug hat Verspätung.",
    "description": "Ihr Zug hat eine Verspätung.\n\nGrund: Ein Zug, der in STRASBOURG vor Ihrem Zug fährt, hat sich verlangsamt.",
    "severity": "slight",
    "affects": [
      {
        "vehicle_journeys": [
          "9572"
        ]
      }
    ]
  },
  {
    "situation_number": "QOM:Broadcast::8529689907128364476:LOC",
    "summary": "    16.06, Saint-Gilles-Croix-de-Vie, Störung eines Bahnübergangs",
    "description": "Verkehrsbehinderungen in beiden Richtungen auf der Strecke Nantes - Challans - St-Gilles-Croix-De-Vie.\n\nStörung eines Bahnübergangs in Saint-Gilles-Croix-de-Vie. Unsere technischen Teams begeben sich an den Sitzplatz.\n\nWiederaufnahme des Verkehrs voraussichtlich um 18.00 Uhr.\n\nÜberprüfen Sie Ihre Fahrpläne.",
    "severity": "slight",
    "affects": [
      {}
    ]
  },
  {
    "situation_number": "QOM:Broadcast::3511540671649389013:LOC",
    "summary": "L'équipage du train n'est pas complet pour assurer le départ à l'heure, il termine sa mission sur un train actuellement en retard.",
    "description": "L'équipage du train n'est pas complet pour assurer le départ à l'heure, il termine sa mission sur un train actuellement en retard.",
    "severity": "slight",
    "affects": [
      {
        "vehicle_journeys": [
          "846555"
        ]
      }
    ]
  },
  {
    "situation_number": "QOM:Broadcast::7440447394037714534:LOC",
    "summary": "L'agent requis pour le départ du train est absent et n'a pas pu être remplacé.",
    "description": "L'agent requis pour le départ du train est absent et n'a pas pu être remplacé.",
    "severity": "slight",
    "affects": [
      {
        "vehicle_journeys": [
          "860746",
          "860722",
          "860719"
        ]
      }
    ]
  },
  {
    "situation_number": "QOM:Broadcast::1292024304306995110:LOC",
    "summary": "Voiture 6 dédiée au placement libre",
    "description": "Voiture 6 dédiée au placement libre",
    "severity": "slight",
    "affects": [
      {
        "vehicle_journeys": [
          "839127"
        ]
      }
    ]
  },
  {
    "situation_number": "QOM:Broadcast::647481378720177832:LOC",
    "summary": "Travaux sur la ligne à grande vitesse en août 2025",
    "description": "",
    "severity": "slight",
    "affects": [
      {}
    ]
  },
  {
    "situation_number": "QOM:Broadcast::2932381052009380518:LOC",
    "summary": "Informationen",
    "description": "Dieser Zug wird vom 30. Juni bis 14. August montags bis freitags nicht verkehren, da das Angebot während der Sommermonate ausgedünnt wird.",
    "severity": "slight",
    "affects": [
      {
        "vehicle_journeys": [
          "831417",
          "96123",
          "830426",
          "96143",
          "831430",
          "96130",
          "96137",
          "830433",
          "96136"
        ]
      }
    ]
  },
  {
    "situation_number": "QOM:Broadcast::7886191890185885576:LOC",
    "summary": "Geplante Arbeiten auf Ihrer Linie",
    "description": "Geplante Arbeiten auf Ihrer Linie",
    "severity": "slight",
    "affects": [
      {
        "vehicle_journeys": [
          "843924",
          "843925",
          "843923",
          "843928",
          "843926",
          "848936",
          "843920",
          "843008",
          "843921",
          "848932",
          "843914",
          "843911",
          "843912",
          "843917",
          "843918",
          "843915",
          "843916",
          "848920",
          "848922",
          "843919",
          "46562",
          "843942",
          "843943",
          "843940",
          "843941",
          "843935",
          "843936",
          "843933",
          "843934",
          "843939",
          "843937",
          "848946",
          "843931",
          "848942",
          "843932",
          "843930",
          "843903",
          "843900",
          "843901",
          "843906",
          "843904",
          "843905",
          "843908",
          "843909"
        ]
      }
    ]
  },
  {
    "situation_number": "QOM:Broadcast::1838870663799849146:LOC",
    "summary": "Voiture 6 dédiée au placement libre",
    "description": "Voiture 6 dédiée au placement libre",
    "severity": "slight",
    "affects": [
      {
        "vehicle_journeys": [
          "839555"
        ]
      }
    ]
  },
  {
    "situation_number": "QOM:Broadcast::8498441789241126239:LOC",
    "summary": "851721 retardé",
    "description": "Votre train 851721  à destination de Dieppe   circule sur une voie unique, il est retenu gare de Longueville sur scie pour laisser passer un train circulant en sens inverse.",
    "severity": "slight",
    "affects": [
      {
        "vehicle_journeys": [
          "851721"
        ]
      }
    ]
  },
  {
    "situation_number": "QOM:Broadcast::6312185553767720952:LOC",
    "summary": "Reprise de la circulation en gare de Périgueux",
    "description": " \n\nLa circulation reprend quasi normalement sur les lignes à destination et en provenance de Périgueux.\n\nMotif : présence d'un bagage délaissé à bord d'un train.\n\nDes retards restent à prévoir. Restez informés via vos outils d'information habituels.",
    "severity": "slight",
    "affects": [
      {
        "vehicle_journeys": [
          "865569",
          "865326",
          "865336",
          "865576",
          "865486",
          "865332",
          "865331",
          "865342",
          "868224",
          "868227",
          "868215",
          "868221",
          "865340",
          "865570"
        ]
      }
    ]
  },
  {
    "situation_number": "QOM:Broadcast::5718347357738609145:LOC",
    "summary": "Betreuung von Fahrgästen mit Anschlusszügen, die aufgrund von Verspätungen den ursprünglich geplanten Zug nicht nehmen konnten.",
    "description": "Betreuung von Fahrgästen mit Anschlusszügen, die aufgrund von Verspätungen den ursprünglich geplanten Zug nicht nehmen konnten.",
    "severity": "slight",
    "affects": [
      {
        "vehicle_journeys": [
          "865342"
        ]
      }
    ]
  },
  {
    "situation_number": "QOM:Broadcast::7625500844690787493:LOC",
    "summary": "Verkehr gestört",
    "description": "Der Verkehr ist gestört. Unsere Teams sind im Einsatz. \n\nUrsache: Ein LKW hat eine Eisenbahnbrücke zwischen TOULOUSE MATABIAU und CARCASONNE  beschädigt.",
    "severity": "slight",
    "affects": [
      {
        "vehicle_journeys": [
          "4657"
        ]
      }
    ]
  },
  {
    "situation_number": "QOM:Broadcast::3696168121271160255:LOC",
    "summary": "Voitures 6 et 16 dédiées au placement libre",
    "description": "Voitures 6 et 16 dédiées au placement libre",
    "severity": "slight",
    "affects": [
      {
        "vehicle_journeys": [
          "839413"
        ]
      }
    ]
  },
  {
    "situation_number": "QOM:Broadcast::7613773450971130658:LOC",
    "summary": "Montag, 16. Juni: Der Zug hat eine neue Route.",
    "description": "Montag, 16. Juni: Dieser Zug wird zwischen Diemeringen und Sarreguemines aufgrund der Schließung des Stellwerks SNCF réseau de Sarreguemines durch Busse ersetzt.\n\nInfos: TER-Website GE, SNCF Connect oder jede andere Mobilitätsanwendung Ihrer Wahl.",
    "severity": "slight",
    "affects": [
      {
        "vehicle_journeys": [
          "830932"
        ]
      }
    ]
  },
  {
    "situation_number": "QOM:Broadcast::1461079457307595728:LOC",
    "summary": "839141: modification de composition",
    "description": "En raison d'une modification,\n\nle matériel assurant votre train 839141 de Paris-Est à 18h36 à Saint-Dizier a été modifié. Veuillez monter à bord du TER sans vous référer au numéro de place repris sur votre titre. Le placement sera libre.",
    "severity": "slight",
    "affects": [
      {
        "vehicle_journeys": [
          "839141"
        ]
      }
    ]
  },
  {
    "situation_number": "QOM:Broadcast::266506696277133076:LOC",
    "summary": "Votre train est retardé.",
    "description": "Votre train est retardé.\n\nCause : retard de votre rame lors de son précédent trajet à MARSEILLE-ST-CHARLES .",
    "severity": "slight",
    "affects": [
      {
        "vehicle_journeys": [
          "9896"
        ]
      }
    ]
  },
  {
    "situation_number": "QOM:Broadcast::8761396337527671714:LOC",
    "summary": "    16.06, Saint-Gilles-Croix-de-Vie, Störung eines Bahnübergangs",
    "description": "Verkehrsbehinderungen in beiden Richtungen auf der Strecke Nantes - Challans - St-Gilles-Croix-De-Vie.\n\nStörung eines Bahnübergangs in Saint-Gilles-Croix-de-Vie. Unsere technischen Teams begeben sich an den Sitzplatz.\n\nWiederaufnahme des Verkehrs voraussichtlich um 18.00 Uhr.\n\nÜberprüfen Sie Ihre Fahrpläne.",
    "severity": "slight",
    "affects": [
      {}
    ]
  },
  {
    "situation_number": "QOM:Broadcast::3879959043743035134:LOC",
    "summary": "860851 : train supprimé",
    "description": "Le train 860851 est supprimé.\n\nPrendre le train 860853 avec arrêt supplémentaire, départ Nevers  (05h53) destination Tours (08h31) pour la suite du voyage.",
    "severity": "slight",
    "affects": [
      {
        "vehicle_journeys": [
          "860851"
        ]
      }
    ]
  },
  {
    "situation_number": "QOM:Broadcast::2076787563751383:LOC",
    "summary": "Für Reisende gesperrter Zug am Hinten des TER 876433, Zugang über die Vorderseite des Zuges.",
    "description": "Der Zug am Hinten Ihres TER 876433 ist geschlossen, der Zugang erfolgt über den vorderen Teil des Zuges.",
    "severity": "slight",
    "affects": [
      {
        "vehicle_journeys": [
          "876433"
        ]
      }
    ]
  },
  {
    "situation_number": "QOM:Broadcast::2567206447584857724:LOC",
    "summary": "Wagen am Bahnsteig im Bahnhof Courville",
    "description": "Bei diesem Zug besteht die Gefahr, dass im Bahnhof Courville-sur-Eure Türen über den Bahnsteig hinausragen. Reisende, die in diesem Bahnhof aussteigen, werden gebeten, sich zum vorderen Teil des Zuges zu begeben.",
    "severity": "slight",
    "affects": [
      {
        "vehicle_journeys": [
          "862523"
        ]
      }
    ]
  },
  {
    "situation_number": "QOM:Broadcast::3448959787130648859:LOC",
    "summary": "Verkehr gestört",
    "description": "Der Verkehr ist gestört. Unsere Teams sind im Einsatz.\n\nUrsache: Signalstörung zwischen NEVERS und SAINCAIZE.",
    "severity": "slight",
    "affects": [
      {
        "vehicle_journeys": [
          "5959"
        ]
      }
    ]
  },
  {
    "situation_number": "QOM:Broadcast::1618229324447908866:LOC",
    "summary": "Panne d'un aiguillage à Malaunay Fin d'incident",
    "description": " Fin d'incident, reprise progressive des circulations entre Rouen et Le havre / Rouen et Dieppe.",
    "severity": "slight",
    "affects": [
      {}
    ]
  },
  {
    "situation_number": "QOM:Broadcast::6736755178121382669:LOC",
    "summary": "Train court.",
    "description": " \n\nVotre train sera un train court. Nous faisons tout pour rétablir cette situation.",
    "severity": "slight",
    "affects": [
      {
        "vehicle_journeys": [
          "23332"
        ]
      }
    ]
  },
  {
    "situation_number": "QOM:Broadcast::2322251120370116583:LOC",
    "summary": "Verkehr gestört",
    "description": "Der Verkehr ist gestört. Unsere Teams sind im Einsatz.\n\nGrund: Ein Weichensystem erfordert Überprüfungen zwischen PARIS AUSTERLITZ  und LES AUBRAIS.",
    "severity": "slight",
    "affects": [
      {
        "vehicle_journeys": [
          "3665",
          "3654"
        ]
      }
    ]
  },
  {
    "situation_number": "QOM:Broadcast::4731922569163672496:LOC",
    "summary": "Ihr Zug hat Verspätung.",
    "description": "Ihr Zug hat Verspätung.\n\nUrsache: Verlangsamung eines Zuges, der vor Ihrem Zug in MASSY TGV verkehrt.",
    "severity": "slight",
    "affects": [
      {
        "vehicle_journeys": [
          "8641",
          "8739"
        ]
      }
    ]
  },
  {
    "situation_number": "QOM:Broadcast::7145333866955502993:LOC",
    "summary": "TER 895857: changement de train à besancon",
    "description": "895857 du 16/06: Un autre matériel sera mis en place au départ de BESANCON .\n\nChangement de train pour la poursuite de votre voyage.",
    "severity": "slight",
    "affects": [
      {
        "vehicle_journeys": [
          "895857"
        ]
      }
    ]
  },
  {
    "situation_number": "QOM:Broadcast::8997559503063969379:LOC",
    "summary": "  16/06 Bourgtheroulde, Présence d'un arbre menaçant de tomber sur les voies",
    "description": "Trafic perturbé entre Elbeuf et Serquigny, dans les deux sens.Motif: Présence d'un arbre menaçant de tomber sur les voies.   Perturbations prévues jusqu'à 19h00",
    "severity": "slight",
    "affects": [
      {
        "vehicle_journeys": [
          "852068",
          "852024",
          "852030",
          "852064"
        ]
      }
    ]
  },
  {
    "situation_number": "QOM:Broadcast::4794343850541243578:LOC",
    "summary": "851727 retardé",
    "description": "Votre train n°851727 à destination de Dieppe , effectue des arrêts supplémentaires en gares de Maromme, Malaunay, St Victor, Longueville, St Aubin, à la suite de la suppression du train n°851725.",
    "severity": "slight",
    "affects": [
      {
        "vehicle_journeys": [
          "851727"
        ]
      }
    ]
  },
  {
    "situation_number": "QOM:Broadcast::6864812043322161015:LOC",
    "summary": "Ihr Zug hat Verspätung.",
    "description": "Ihr Zug hat eine Verspätung.\n\nGrund: Ein Zug, der in PARIS vor Ihrem Zug fährt, hat sich verlangsamt.",
    "severity": "slight",
    "affects": [
      {
        "vehicle_journeys": [
          "8477",
          "8551"
        ]
      }
    ]
  },
  {
    "situation_number": "QOM:Broadcast::3836440075230062554:LOC",
    "summary": "Reprise des circulations sur la ligne Paris - Clermont et Lyon - Nantes",
    "description": "",
    "severity": "slight",
    "affects": [
      {}
    ]
  },
  {
    "situation_number": "QOM:Broadcast::5310079856900087083:LOC",
    "summary": "Ausstattung im Bahnhof   : außer Betrieb",
    "description": "Bahnhof  : Der Fahrkartenautomat ist außer Betrieb.\n\n Die Störung wird berücksichtigt. Wir danken Ihnen für Ihr Verständnis.",
    "severity": "slight",
    "affects": [
      {
        "vehicle_journeys": [
          "43406",
          "841228",
          "841822",
          "43405",
          "841227",
          "841821",
          "841824",
          "43407",
          "841229",
          "841823",
          "841826",
          "841825",
          "43404",
          "841827",
          "841222",
          "841221",
          "841224",
          "841223",
          "841226",
          "841820",
          "841225",
          "841271",
          "439068",
          "841811",
          "841813",
          "841812",
          "841815",
          "841814",
          "841817",
          "841816",
          "841253",
          "841252",
          "841254",
          "439113",
          "439112",
          "841819",
          "841818",
          "841921",
          "841920",
          "841249",
          "841923",
          "841922",
          "841925",
          "841924",
          "841242",
          "841241",
          "841244",
          "841243",
          "841246",
          "841245",
          "841248",
          "841247",
          "439121",
          "841251",
          "841250",
          "841809",
          "841239",
          "841238",
          "841912",
          "841911",
          "841914",
          "841913",
          "841916",
          "841915",
          "841231",
          "841230",
          "841233",
          "841232",
          "841235",
          "841234",
          "841237",
          "841236",
          "841240",
          "841918",
          "841917",
          "841919"
        ]
      }
    ]
  },
  {
    "situation_number": "QOM:Broadcast::1405964553897444665:LOC",
    "summary": "Voiture 6 dédiée au placement libre",
    "description": "Voiture 6 dédiée au placement libre",
    "severity": "slight",
    "affects": [
      {
        "vehicle_journeys": [
          "839505"
        ]
      }
    ]
  },
  {
    "situation_number": "QOM:Broadcast::8470965223145114634:LOC",
    "summary": "Voiture 6 dédiée au placement libre",
    "description": "Voiture 6 dédiée au placement libre",
    "severity": "slight",
    "affects": [
      {
        "vehicle_journeys": [
          "839551"
        ]
      }
    ]
  },
  {
    "situation_number": "QOM:Broadcast::1650138507090133224:LOC",
    "summary": "851723 retardé",
    "description": "Votre train 851723  à destination de DIeppe   circule sur une voie unique, il est retenu gare de Auffay pour laisser passer un train circulant en sens inverse.",
    "severity": "slight",
    "affects": [
      {
        "vehicle_journeys": [
          "851723"
        ]
      }
    ]
  },
  {
    "situation_number": "QOM:Broadcast::5551966026879223772:LOC",
    "summary": "Travaux en cours.",
    "description": "Du 12/07 au 14/09, aucun train ne circulera entre Luxembourg et Bettembourg (travaux CFL).\n\nAchetez votre billet en saisissant comme destination la gare de Bettembourg.\n\nDes bus de remplacements gratuits sont mis en place entre Luxembourg et Bettembourg.",
    "severity": "slight",
    "affects": [
      {}
    ]
  },
  {
    "situation_number": "QOM:Broadcast::2642447972987226313:LOC",
    "summary": "Ihr Zug hat Verspätung.",
    "description": "Ihr Zug hat eine Verspätung.\n\nGrund: Die Schranken eines Bahnübergangs zwischen LES ARCS  und TOULON  müssen überprüft werden.",
    "severity": "slight",
    "affects": [
      {
        "vehicle_journeys": [
          "5772",
          "5792"
        ]
      }
    ]
  },
  {
    "situation_number": "QOM:Broadcast::9096919285782253836:LOC",
    "summary": "Arrêt(s) non desservi(s).",
    "description": ": 865464 du 17/06 supprimé de Mussidan à Périgueux .\n\n \n\nMise en place de taxi à la demande  .",
    "severity": "slight",
    "affects": [
      {
        "vehicle_journeys": [
          "865464"
        ]
      }
    ]
  },
  {
    "situation_number": "QOM:Broadcast::8800921246838728244:LOC",
    "summary": "Bitte beachten Sie, dass Ihr Zug einige Bahnhöfe nicht anfährt.",
    "description": "Ihr Zug bedient einige Bahnhöfe nicht.\n\nGrund: Ein Zug, der vor Ihrem Zug in DOUAI fährt, hat die Geschwindigkeit verringert.",
    "severity": "slight",
    "affects": [
      {
        "vehicle_journeys": [
          "5192"
        ]
      }
    ]
  },
  {
    "situation_number": "QOM:Broadcast::6873809751946313166:LOC",
    "summary": "Der Zug gelöscht",
    "description": "Ihr Zug wird gelöscht.\n\nGrund: Materialmangel aufgrund von Wartungsarbeiten in BORDEAUX SAINT JEAN.",
    "severity": "slight",
    "affects": [
      {
        "vehicle_journeys": [
          "4657"
        ]
      }
    ]
  },
  {
    "situation_number": "QOM:Broadcast::6447562453749928248:LOC",
    "summary": "TER retardé : défaillance matériel",
    "description": "Le TER 854058 est actuellement immobilisé à  Janzé . Le conducteur procède a des vérifications techniques.",
    "severity": "slight",
    "affects": [
      {
        "vehicle_journeys": [
          "854058"
        ]
      }
    ]
  },
  {
    "situation_number": "QOM:Broadcast::4789633834530054900:LOC",
    "summary": "Capacité réduite.",
    "description": "Capacité du train n° 886607 du 17/06 réduite.",
    "severity": "slight",
    "affects": [
      {
        "vehicle_journeys": [
          "886607"
        ]
      }
    ]
  },
  {
    "situation_number": "QOM:Broadcast::2370620925585089836:LOC",
    "summary": "Ihr Zug hat Verspätung.",
    "description": "Ihr Zug hat eine Verspätung.\n\nGrund: Ein Zug, der vor Ihrem Zug in LYON PART DIEU verkehrt, hat sich verlangsamt.",
    "severity": "slight",
    "affects": [
      {
        "vehicle_journeys": [
          "9882",
          "5182"
        ]
      }
    ]
  },
  {
    "situation_number": "QOM:Broadcast::5909209051621073399:LOC",
    "summary": "839130: modification de composition",
    "description": "En raison d'une modification,\n\nle matériel assurant votre train 839130 deSaint-Dizier à 05h33 du 17/06 à Paris-Est a été modifié. Veuillez monter à bord du TER sans vous référer au numéro de place repris sur votre titre. Le placement sera libre.",
    "severity": "slight",
    "affects": [
      {
        "vehicle_journeys": [
          "839130"
        ]
      }
    ]
  },
  {
    "situation_number": "QOM:Broadcast::451136705296664122:LOC",
    "summary": "TOILETTES HORS SERVICE",
    "description": "Nous vous informons que les toilettes à bord de votre train ZOU sont hors service.\n\nVeuillez nous excuser pour la gêne occasionnée.",
    "severity": "slight",
    "affects": [
      {
        "vehicle_journeys": [
          "881182",
          "86056",
          "86045",
          "86069",
          "86032"
        ]
      }
    ]
  },
  {
    "situation_number": "QOM:Broadcast::2233669338562575563:LOC",
    "summary": "Voitures 6, 11, 12 et 16 dédiées au placement libre",
    "description": "Voitures 6, 11, 12 et 16 dédiées au placement libre",
    "severity": "slight",
    "affects": [
      {
        "vehicle_journeys": [
          "839407"
        ]
      }
    ]
  },
  {
    "situation_number": "QOM:Broadcast::2696849728561924894:LOC",
    "summary": "Ihr Zug hat Verspätung.",
    "description": "Ihr Zug hat Verspätung.\n\nGrund: Die Verspätung Ihres Zuges bei seiner vorherigen Fahrt nach PARIS EST.",
    "severity": "slight",
    "affects": [
      {
        "vehicle_journeys": [
          "2747"
        ]
      }
    ]
  },
  {
    "situation_number": "QOM:Broadcast::7681097422464261415:LOC",
    "summary": "Ihr Zug hat Verspätung.",
    "description": "Ihr Zug hat eine Verspätung.\n\nGrund: Schwierigkeiten bei der Bildung des Zuges in PARIS EST.",
    "severity": "slight",
    "affects": [
      {
        "vehicle_journeys": [
          "2513"
        ]
      }
    ]
  },
  {
    "situation_number": "QOM:Broadcast::1406656344646746480:LOC",
    "summary": "Voiture 16 dédiée au placement libre",
    "description": "Voiture 16 dédiée au placement libre",
    "severity": "slight",
    "affects": [
      {
        "vehicle_journeys": [
          "840857"
        ]
      }
    ]
  },
  {
    "situation_number": "QOM:Broadcast::4506174827201234949:LOC",
    "summary": "Ihr Zug hat Verspätung.",
    "description": "Ihr Zug hat Verspätung.\n\nGrund: Ein Zug, der in NANTES vor Ihrem Zug fährt, verlangsamt sich.",
    "severity": "slight",
    "affects": [
      {
        "vehicle_journeys": [
          "8985",
          "8931"
        ]
      }
    ]
  },
  {
    "situation_number": "QOM:Broadcast::4620172995276334191:LOC",
    "summary": "Der Zug verspätet sich.",
    "description": "Ihr Zug hat eine Verspätung.\n\nGrund: Wartungsarbeiten, die in PARIS MONTPARNASSE verspätet abgeschlossen wurden.",
    "severity": "slight",
    "affects": [
      {
        "vehicle_journeys": [
          "8593",
          "8519"
        ]
      }
    ]
  },
  {
    "situation_number": "QOM:Broadcast::5388178878756683937:LOC",
    "summary": "Der Verkehr wird allmählich wieder aufgenommen.",
    "description": "Der Verkehr wird allmählich wieder aufgenommen.\n\nMit einigen Verspätungen ist noch zu rechnen.\n\nUrsache: Einrichtung eines Sicherheitsperimeters, der die Verspätung der Züge zwischen AGEN und MONTAUBAN VILLE verursacht.",
    "severity": "slight",
    "affects": [
      {
        "vehicle_journeys": [
          "4659"
        ]
      }
    ]
  },
  {
    "situation_number": "QOM:Broadcast::3197554110554144235:LOC",
    "summary": "Voiture 6 dédiée au placement libre",
    "description": "Voiture 6 dédiée au placement libre",
    "severity": "slight",
    "affects": [
      {
        "vehicle_journeys": [
          "839103"
        ]
      }
    ]
  },
  {
    "situation_number": "QOM:Broadcast::618234008710205356:LOC",
    "summary": "Aufgrund zusätzlicher Wartungsarbeiten müssen wir die normale Route des Zuges ändern.",
    "description": "Aufgrund zusätzlicher Wartungsarbeiten müssen wir die normale Route des Zuges ändern.",
    "severity": "slight",
    "affects": [
      {
        "vehicle_journeys": [
          "86382"
        ]
      }
    ]
  },
  {
    "situation_number": "QOM:Broadcast::6963637985161923916:LOC",
    "summary": "Voitures 6 et 16 dédiées au placement libre",
    "description": "Voitures 6 et 16 dédiées au placement libre",
    "severity": "slight",
    "affects": [
      {
        "vehicle_journeys": [
          "839139"
        ]
      }
    ]
  },
  {
    "situation_number": "QOM:Broadcast::5712898151563740554:LOC",
    "summary": "Voiture 6 dédiée au placement libre",
    "description": "Voiture 6 dédiée au placement libre",
    "severity": "slight",
    "affects": [
      {
        "vehicle_journeys": [
          "839405"
        ]
      }
    ]
  },
  {
    "situation_number": "QOM:Broadcast::2875478119236266346:LOC",
    "summary": "Ihr Sitzplatz im vorderen Teil des Zuges für Reisende mit dem Reiseziel Meyrargues.",
    "description": "Eine oder mehrere Türen Ihres TER ZOU 17418 werden nicht am Bahnsteig im Bahnhof Meyrargues angehalten. Reisende mit Reiseziel Das Reiseziel werden gebeten, im vorderen Teil des Zuges einzusteigen.",
    "severity": "slight",
    "affects": [
      {
        "vehicle_journeys": [
          "17418"
        ]
      }
    ]
  },
  {
    "situation_number": "QOM:Broadcast::7804087932559787928:LOC",
    "summary": "Train 854247  finalement non supprimé.",
    "description": "Votre TER 854247    circule normalement.",
    "severity": "slight",
    "affects": [
      {
        "vehicle_journeys": [
          "854247"
        ]
      }
    ]
  },
  {
    "situation_number": "QOM:Broadcast::2237124982542948469:LOC",
    "summary": "Samedi 28 au dimanche 29 juin 1h30 du matin,  interruption de circulation entre Paris Montparnasse et Versailles Chantiers.",
    "description": "Du samedi 28 au dimanche 29 juin à 1h30, travaux du Grand Paris Express, interruption totale du trafic entre Paris et Versailles chantiers. Programme en ligne, sur les applications de mobilité, internet, le fil Twitter @RemiTrainPCLM ou au 0 806 70 33 33.",
    "severity": "slight",
    "affects": [
      {
        "vehicle_journeys": [
          "862565",
          "862444",
          "862566",
          "862563",
          "862443",
          "862562",
          "862441",
          "862560",
          "862449",
          "862568",
          "862447",
          "862577",
          "862574",
          "862451",
          "862573",
          "862570",
          "862450",
          "862579",
          "862543",
          "862422",
          "862421",
          "862540",
          "862429",
          "862426",
          "862427",
          "862545",
          "862425",
          "862554",
          "862433",
          "862555",
          "862434",
          "862552",
          "862431",
          "862432",
          "862551",
          "862430",
          "862439",
          "862437",
          "862559",
          "862438",
          "862435",
          "862436",
          "862400",
          "862401",
          "862520",
          "862529",
          "862408",
          "862409",
          "862527",
          "862406",
          "862528",
          "862404",
          "862526",
          "862523",
          "862402",
          "862524",
          "862403",
          "862532",
          "862411",
          "862412",
          "862531",
          "862410",
          "862417",
          "862418",
          "862536",
          "862416",
          "862413",
          "862535",
          "862500",
          "862507",
          "862508",
          "862506",
          "862504",
          "862502",
          "862511",
          "862519",
          "862516",
          "862515",
          "862512",
          "862482",
          "862466",
          "862587",
          "862467",
          "862585",
          "862464",
          "862583",
          "862462",
          "862463",
          "862581",
          "862460",
          "862582",
          "862468",
          "862471",
          "862472",
          "862479",
          "862481"
        ]
      }
    ]
  },
  {
    "situation_number": "QOM:Broadcast::1556143776025548409:LOC",
    "summary": "Ihr Zug hat Verspätung.",
    "description": "Ihr Zug hat Verspätung.\n\nGrund: Der Gesundheitszustand eines Reisenden an Bord Ihres Zuges erfordert den Einsatz der Feuerwehr in BORDEAUX SAINT JEAN.",
    "severity": "slight",
    "affects": [
      {
        "vehicle_journeys": [
          "4669"
        ]
      }
    ]
  },
  {
    "situation_number": "QOM:Broadcast::6045336336117180616:LOC",
    "summary": "TER 892009: changement de train à laroche",
    "description": "892009 du 16/06: Un autre matériel sera mis en place au départ de LAROCHE .\n\nChangement de train pour la poursuite de votre voyage.",
    "severity": "slight",
    "affects": [
      {
        "vehicle_journeys": [
          "892009"
        ]
      }
    ]
  },
  {
    "situation_number": "QOM:Broadcast::148740536099441884:LOC",
    "summary": "Ihr Zug hat Verspätung.",
    "description": "Ihr Zug hat Verspätung.\n\nGrund: Ein Zug, der vor Ihrem Zug in ROUFFAC verkehrt, hat sich verlangsamt.",
    "severity": "slight",
    "affects": [
      {
        "vehicle_journeys": [
          "9879"
        ]
      }
    ]
  },
  {
    "situation_number": "QOM:Broadcast::237176087869941334:LOC",
    "summary": "Voitures 6 et 16 dédiées au placement libre",
    "description": "Voitures 6 et 16 dédiées au placement libre",
    "severity": "slight",
    "affects": [
      {
        "vehicle_journeys": [
          "839131"
        ]
      }
    ]
  },
  {
    "situation_number": "QOM:Broadcast::5885317586154903088:LOC",
    "summary": "Ihr Zug hat Verspätung.",
    "description": "Ihr Zug hat Verspätung.\n\nGrund: Schwierigkeiten bei der Bildung des Zuges in MARSEILLE ST CHARLES .",
    "severity": "slight",
    "affects": [
      {
        "vehicle_journeys": [
          "4770"
        ]
      }
    ]
  },
  {
    "situation_number": "QOM:Broadcast::7560071864900042299:LOC",
    "summary": "860722 : train supprimé",
    "description": "Le train 860722 est supprimé.\n\nPrendre le train 860808 départ de la gare de Tours à 20h53.",
    "severity": "slight",
    "affects": [
      {
        "vehicle_journeys": [
          "860722"
        ]
      }
    ]
  },
  {
    "situation_number": "QOM:Broadcast::1981530710912601364:LOC",
    "summary": "Ihr Zug hat Verspätung.",
    "description": "Ihr Zug hat Verspätung.\n\nGrund: Ihr Zug blieb länger als geplant auf dem Bahnsteig stehen, um einen Reisenden in SAINT GERMAIN DES FOSSÉS  zu betreuen.",
    "severity": "slight",
    "affects": [
      {
        "vehicle_journeys": [
          "4502"
        ]
      }
    ]
  },
  {
    "situation_number": "QOM:Broadcast::7209897917646808106:LOC",
    "summary": "Samedi 28 au dimanche 29 juin 1h30 du matin,  interruption de circulation entre Paris Montparnasse et Versailles Chantiers.",
    "description": "Du samedi 28 au dimanche 29 juin à 1h30, travaux du Grand Paris Express, interruption totale du trafic entre Paris et Versailles chantiers. Programme en ligne, sur les applications de mobilité, internet, le fil Twitter @RemiTrainPCLM ou au 0 806 70 33 33.",
    "severity": "slight",
    "affects": [
      {}
    ]
  },
  {
    "situation_number": "QOM:Broadcast::5810136426114800386:LOC",
    "summary": " : Votre TER du 17/06 est supprimé.",
    "description": " : Votre TER du 17/06 est supprimé.\n\nDes solutions plus adaptées à votre voyage peuvent être disponibles. Pour cela, rendez-vous sur votre site TER Nouvelle-Aquitaine, sur SNCF Connect ou toute autre application de mobilité.",
    "severity": "slight",
    "affects": [
      {
        "vehicle_journeys": [
          "865700"
        ]
      }
    ]
  },
  {
    "situation_number": "QOM:Broadcast::7317437197417658972:LOC",
    "summary": "860746 : train supprimé",
    "description": "Le train 860746 est supprimé.\n\nPrendre le train 860844 départ de Tours 17h29 ou 860718 départ 17h54 selon desserte.",
    "severity": "slight",
    "affects": [
      {
        "vehicle_journeys": [
          "860746"
        ]
      }
    ]
  },
  {
    "situation_number": "QOM:Broadcast::2173477721527288974:LOC",
    "summary": "Une panne sur le train entraîne sa suppression.",
    "description": "Une panne sur le train entraîne sa suppression.",
    "severity": "slight",
    "affects": [
      {
        "vehicle_journeys": [
          "842204"
        ]
      }
    ]
  },
  {
    "situation_number": "QOM:Broadcast::5444065987217479407:LOC",
    "summary": "Ihr Zug hat Verspätung.",
    "description": "Ihr Zug hat eine Verspätung.\n\nGrund: Verzögerung eines Zuges, der vor Ihrem Zug zwischen MELUN und NEVERS verkehrt.",
    "severity": "slight",
    "affects": [
      {
        "vehicle_journeys": [
          "5983"
        ]
      }
    ]
  },
  {
    "situation_number": "QOM:Broadcast::4667557212237809440:LOC",
    "summary": "Voiture 6 dédiée au placement libre",
    "description": "Voiture 6 dédiée au placement libre",
    "severity": "slight",
    "affects": [
      {
        "vehicle_journeys": [
          "839401"
        ]
      }
    ]
  },
  {
    "situation_number": "QOM:Broadcast::3296204280860229388:LOC",
    "summary": "Voiture 6 dédiée au placement libre",
    "description": "Voiture 6 dédiée au placement libre",
    "severity": "slight",
    "affects": [
      {
        "vehicle_journeys": [
          "839115"
        ]
      }
    ]
  },
  {
    "situation_number": "QOM:Broadcast::2501508752642767369:LOC",
    "summary": "Ihr Zug hat Verspätung.",
    "description": "Ihr Zug hat eine Verspätung.\n\nGrund: Verlangsamung eines Zuges, der vor Ihrem Zug zwischen BORDEAUX und PARIS MONTPARNASSE verkehrt.",
    "severity": "slight",
    "affects": [
      {
        "vehicle_journeys": [
          "8586",
          "8550"
        ]
      }
    ]
  },
  {
    "situation_number": "QOM:Broadcast::2739246150827136597:LOC",
    "summary": "848963 retardé",
    "description": "Votre train 848963 \nà destination de Rouen est retenu en gare de Amiens.\nMotif: Saturation des voies en gare.",
    "severity": "slight",
    "affects": [
      {
        "vehicle_journeys": [
          "848963"
        ]
      }
    ]
  },
  {
    "situation_number": "QOM:Broadcast::3143505637452756110:LOC",
    "summary": "Voiture 6 dédiée au placement libre",
    "description": "Voiture 6 dédiée au placement libre",
    "severity": "slight",
    "affects": [
      {
        "vehicle_journeys": [
          "839559"
        ]
      }
    ]
  },
  {
    "situation_number": "QOM:Broadcast::7250026792331544032:LOC",
    "summary": "La panne du train nécessite un transfert des voyageurs vers un autre train.",
    "description": "La panne du train nécessite un transfert des voyageurs vers un autre train.",
    "severity": "slight",
    "affects": [
      {
        "vehicle_journeys": [
          "841924"
        ]
      }
    ]
  },
  {
    "situation_number": "QOM:Broadcast::3771052581525975163:LOC",
    "summary": "Trafic interrompu sur l'axe Rodez Capdenac",
    "description": "",
    "severity": "slight",
    "affects": [
      {
        "vehicle_journeys": [
          "870150",
          "870001",
          "462000",
          "870000",
          "870153",
          "870021",
          "461901",
          "870169"
        ]
      }
    ]
  },
  {
    "situation_number": "QOM:Broadcast::2865603362559050319:LOC",
    "summary": "Ihr Zug hat Verspätung.",
    "description": "Ihr Zug hat eine Verspätung.\n\nGrund: Der Triebfahrzeugführer Ihres Zuges hat es geschafft, sich in BORDEAUX SAINT JEAN auszuhelfen.",
    "severity": "slight",
    "affects": [
      {
        "vehicle_journeys": [
          "3856"
        ]
      }
    ]
  },
  {
    "situation_number": "QOM:Broadcast::6080290565652360519:LOC",
    "summary": "AFFLUENCE3",
    "description": "Ce train circulera le mardi 17 juin avec un nombre réduit de places.",
    "severity": "slight",
    "affects": [
      {
        "vehicle_journeys": [
          "844104",
          "842472",
          "844902"
        ]
      }
    ]
  },
  {
    "situation_number": "QOM:Broadcast::6305216361668296030:LOC",
    "summary": "",
    "description": "\n\n Ihr TER vom 17.06. fährt ab Bergerac.\n\nGehen Sie auf Ihre TER-Website Nouvelle-Aquitaine, auf SNCF Connect oder jede andere Mobilitätsanwendung.",
    "severity": "slight",
    "affects": [
      {
        "vehicle_journeys": [
          "865744"
        ]
      }
    ]
  },
  {
    "situation_number": "QOM:Broadcast::4770865785489962100:LOC",
    "summary": "851719 retardé",
    "description": "Votre train n°851719 à destination de Dieppe , effectue des arrêts supplémentaires en gares de Maromme, Malaunay, St Victor, Longueville, St Aubin, à la suite de la suppression du train n°851717.",
    "severity": "slight",
    "affects": [
      {
        "vehicle_journeys": [
          "851719"
        ]
      }
    ]
  },
  {
    "situation_number": "QOM:Broadcast::325117799561544365:LOC",
    "summary": "Panne d'un aiguillage à Malaunay Fin d'incident",
    "description": " Fin d'incident, reprise progressive des circulations entre Rouen et Le havre / Rouen et Dieppe.",
    "severity": "slight",
    "affects": [
      {
        "vehicle_journeys": [
          "850619",
          "851719",
          "850618",
          "850620",
          "850410",
          "3126",
          "851717",
          "851738",
          "851715",
          "3122",
          "851724",
          "850624",
          "850622",
          "851722",
          "850412"
        ]
      }
    ]
  },
  {
    "situation_number": "QOM:Broadcast::3162297519656867273:LOC",
    "summary": "Ihr Zug hat Verspätung.",
    "description": "Ihr Zug hat eine Verspätung.\n\nGrund: Die Schranken eines Bahnübergangs müssen in LA PAULINE-HYÈRES überprüft werden.",
    "severity": "slight",
    "affects": [
      {
        "vehicle_journeys": [
          "6177",
          "6180"
        ]
      }
    ]
  },
  {
    "situation_number": "QOM:Broadcast::9026307637478012566:LOC",
    "summary": "Voiture 6 dédiée au placement libre",
    "description": "Voiture 6 dédiée au placement libre",
    "severity": "slight",
    "affects": [
      {
        "vehicle_journeys": [
          "839557"
        ]
      }
    ]
  },
  {
    "situation_number": "QOM:Broadcast::1862948700274910892:LOC",
    "summary": "860360 : train remis en circulation.",
    "description": "Contrairement à ce qui a été indiqué, le train 860360 circule normalement ce jour.",
    "severity": "slight",
    "affects": [
      {
        "vehicle_journeys": [
          "860360"
        ]
      }
    ]
  },
  {
    "situation_number": "QOM:Broadcast::8225615265993315304:LOC",
    "summary": "Terminus exceptionnel BESANCON",
    "description": "Terminus exceptionnel BESANCON. Les voyageurs à destination de BELFORT-VILLE sont invités à emprunter le TER 894107 Départ de BESANCON 12h32.",
    "severity": "slight",
    "affects": [
      {
        "vehicle_journeys": [
          "895804"
        ]
      }
    ]
  },
  {
    "situation_number": "QOM:Broadcast::6795211081144813469:LOC",
    "summary": "Joué-lès-Tours: Bahnhof geschlossen und/oder DBR HS",
    "description": "Joué-lès-Tours\n\nSchalter den ganzen Tag geschlossen und DBR HS. Kein Verkauf im Bahnhof möglich.",
    "severity": "slight",
    "affects": [
      {
        "stop_points": [
          "87571885"
        ]
      }
    ]
  },
  {
    "situation_number": "QOM:Broadcast::4892934861728997587:LOC",
    "summary": "Suppression TER avec report TER",
    "description": "Ce TER  est supprimé le mardi 17 juin. Report TER P60 Jeumont 06h40 Valenciennes 07h39",
    "severity": "slight",
    "affects": [
      {
        "vehicle_journeys": [
          "841502"
        ]
      }
    ]
  },
  {
    "situation_number": "QOM:Broadcast::6085289754905219471:LOC",
    "summary": "Une panne sur le train entraîne sa suppression.",
    "description": "Une panne sur le train entraîne sa suppression.",
    "severity": "slight",
    "affects": [
      {
        "vehicle_journeys": [
          "855303"
        ]
      }
    ]
  },
  {
    "situation_number": "QOM:Broadcast::4476981416469201819:LOC",
    "summary": "855303 : suppression",
    "description": "TER 855303 supprimé.\n\nReport des clients sur minibus (mêmes arrêts)",
    "severity": "slight",
    "affects": [
      {
        "vehicle_journeys": [
          "855303"
        ]
      }
    ]
  },
  {
    "situation_number": "QOM:Broadcast::6549817758100898345:LOC",
    "summary": "Ihr Zug hat Verspätung.",
    "description": "Ihr Zug hat eine Verspätung.\n\nGrund: Die Verspätung Ihres Zuges bei seiner vorherigen Fahrt nach PARIS AUSTERLITZ.",
    "severity": "slight",
    "affects": [
      {
        "vehicle_journeys": [
          "4097"
        ]
      }
    ]
  },
  {
    "situation_number": "QOM:Broadcast::2951393973136736432:LOC",
    "summary": "Capacité réduite.",
    "description": "Capacité du train n° 889655 du 17/06 réduite.",
    "severity": "slight",
    "affects": [
      {
        "vehicle_journeys": [
          "889655"
        ]
      }
    ]
  },
  {
    "situation_number": "QOM:Broadcast::5489387539433141011:LOC",
    "summary": "Suppression TER avec report TER",
    "description": "Ce TER  est supprimé le mardi 17 juin. Report TER K51 Lens 08h52 Lille Flandres 09h34",
    "severity": "slight",
    "affects": [
      {
        "vehicle_journeys": [
          "842204"
        ]
      }
    ]
  },
  {
    "situation_number": "QOM:Broadcast::1976697783454345056:LOC",
    "summary": "Suppression TER avec report TER",
    "description": "Ce TER est supprimé. Report TER C70 Lille Flandres 16h53 Hazebrouck 17h39 \n\nPanne du train entrainant sa suppression",
    "severity": "slight",
    "affects": [
      {
        "vehicle_journeys": [
          "844125"
        ]
      }
    ]
  },
  {
    "situation_number": "QOM:Broadcast::7846709556744330453:LOC",
    "summary": "Aufgrund der großen Menge an Zügen, die sich in der Wartung befinden, kann der Zug nicht weiterfahren.",
    "description": "Aufgrund der großen Menge an Zügen, die sich in der Wartung befinden, kann der Zug nicht weiterfahren.",
    "severity": "slight",
    "affects": [
      {
        "vehicle_journeys": [
          "860851"
        ]
      }
    ]
  },
  {
    "situation_number": "QOM:Broadcast::5225298791960009036:LOC",
    "summary": "Verkehr stark beeinträchtigt",
    "description": "Der Verkehr ist stark beeinträchtigt. Unsere Teams sind im Einsatz.\n\nGrund: Ein Weichensystem muss zwischen PARIS AUSTERLITZ  und LES AUBRAIS  überprüft werden.",
    "severity": "slight",
    "affects": [
      {
        "vehicle_journeys": [
          "3675"
        ]
      }
    ]
  },
  {
    "situation_number": "QOM:Broadcast::9217889918063773678:LOC",
    "summary": "Le trafic reprend progressivement.",
    "description": "Le trafic reprend progressivement.\n\nQuelques retards sont encore à prévoir.\n\nCause : panne d'un autre train sur la ligne affectant la circulation à MIRAMAS.",
    "severity": "slight",
    "affects": [
      {
        "vehicle_journeys": [
          "4756"
        ]
      }
    ]
  },
  {
    "situation_number": "QOM:Broadcast::5171035461414876264:LOC",
    "summary": "Der Zug wurde aufgrund der Verspätung auf einer früheren Fahrt erst spät bereitgestellt.",
    "description": "Der Zug wurde aufgrund der Verspätung auf einer früheren Fahrt erst spät bereitgestellt.",
    "severity": "slight",
    "affects": [
      {
        "vehicle_journeys": [
          "839559"
        ]
      }
    ]
  },
  {
    "situation_number": "QOM:Broadcast::3308942995686979275:LOC",
    "summary": "839132: modification de composition",
    "description": "En raison d'une modification,\n\nle matériel assurant votre train 839132 deSaint-Dizier à 06h33 du 17/06 à Paris-Est a été modifié. Veuillez monter à bord du TER sans vous référer au numéro de place repris sur votre titre. Le placement sera libre.",
    "severity": "slight",
    "affects": [
      {
        "vehicle_journeys": [
          "839132"
        ]
      }
    ]
  },
  {
    "situation_number": "QOM:Broadcast::9027246872114011798:LOC",
    "summary": " 16.06, Ecommoy, Hindernis auf dem Gleis",
    "description": "Verkehrsbehinderungen in Richtung Le Mans - Château-du-Loir, auf der Strecke Tours - Le Mans - Alençon, Alençon - Le Mans - Tours bis zum Betriebsende.\n\nHindernis auf dem Gleis in Ecommoy.\n\nUnsere technischen Teams sind im Einsatz.",
    "severity": "slight",
    "affects": [
      {
        "vehicle_journeys": [
          "857028",
          "857040",
          "857016"
        ]
      }
    ]
  },
  {
    "situation_number": "QOM:Broadcast::7959770246556613278:LOC",
    "summary": "Der Verkehr ist gestört.",
    "description": "Der Verkehr ist gestört. Unsere Teams sind im Einsatz.\n\nUrsache: Einrichtung eines Sicherheitsbereichs, der den Zugverkehr in PARIS GARE DE LYON verzögert.",
    "severity": "slight",
    "affects": [
      {
        "vehicle_journeys": [
          "6715",
          "9789"
        ]
      }
    ]
  }
]