[
  {
    "situation_number": "QOM:Broadcast::9020708471829056148:LOC",
    "summary": "Meung-sur-Loire: Änderung der Verkaufsbedingungen",
    "description": "Meung-sur-Loire\n\nSchalter den ganzen Tag über geschlossen. Verkauf nur an den Terminals möglich.",
    "severity": "slight",
    "affects": [
      {
        "stop_points": [
          "87574137"
        ]
      }
    ]
  },
  {
    "situation_number": "QOM:Broadcast::3026603499627772381:LOC",
    "summary": "Achse TOULOUSE - LATOUR DE CAROL",
    "description": "Achse TOULOUSE - LATOUR DE CAROL",
    "severity": "slight",
    "affects": [
      {
        "vehicle_journeys": [
          "871914",
          "871915",
          "871910",
          "871911",
          "871912",
          "871913",
          "871907",
          "871908",
          "871909",
          "871903",
          "871904",
          "871905",
          "871906",
          "871900",
          "871901",
          "871902",
          "871976",
          "871977",
          "871978",
          "871979",
          "871974",
          "871975",
          "871980",
          "871981",
          "871982",
          "871989",
          "871983",
          "871986",
          "462498",
          "462499",
          "462494",
          "462495",
          "462496",
          "462479",
          "871472",
          "462486",
          "871471",
          "462487",
          "871470",
          "462489",
          "871476",
          "462482",
          "871475",
          "462483",
          "871474",
          "462484",
          "871473",
          "462485",
          "871479",
          "871478",
          "462480",
          "871477",
          "462481",
          "462468",
          "462469",
          "871483",
          "462475",
          "871482",
          "462476",
          "871481",
          "462477",
          "871480",
          "462478",
          "462471",
          "871486",
          "871485",
          "462473",
          "871484",
          "462474",
          "871489",
          "462470",
          "462458",
          "462459",
          "871450",
          "462464",
          "462465",
          "871454",
          "462460",
          "871453",
          "462461",
          "871452",
          "871451",
          "462463",
          "871458",
          "871457",
          "871456",
          "871455",
          "871459",
          "462449",
          "871461",
          "462453",
          "871460",
          "462455",
          "462456",
          "871465",
          "871464",
          "462450",
          "871463",
          "462451",
          "871462",
          "462452",
          "871468",
          "79018",
          "79016",
          "79020",
          "462439",
          "462443",
          "462440",
          "462441",
          "462426",
          "462431",
          "462433",
          "462430",
          "871419",
          "462418",
          "462419",
          "462413",
          "462414",
          "462420",
          "462423",
          "871410",
          "871414",
          "871413",
          "871412",
          "871411",
          "871417",
          "871416",
          "871415",
          "462408",
          "462409",
          "462410",
          "462412",
          "871421",
          "871425",
          "871423",
          "871429",
          "871409",
          "871408",
          "871403",
          "871402",
          "871401",
          "871400",
          "871407",
          "871406",
          "871405",
          "871404",
          "73109",
          "73103",
          "73101",
          "73100"
        ]
      }
    ]
  },
  {
    "situation_number": "QOM:Broadcast::569344591753686399:LOC",
    "summary": "Weitere Informationen:",
    "description": "",
    "severity": "slight",
    "affects": [
      {
        "vehicle_journeys": [
          "891208"
        ]
      }
    ]
  },
  {
    "situation_number": "QOM:Broadcast::7376333457552118828:LOC",
    "summary": "Weitere Informationen :",
    "description": "",
    "severity": "slight",
    "affects": [
      {
        "vehicle_journeys": [
          "843100"
        ]
      }
    ]
  },
  {
    "situation_number": "QOM:Broadcast::8743301144370208063:LOC",
    "summary": "TER supprimé.",
    "description": "Défaillance de matériel - 17503  : Votre train ne circulera pas le 17 mars.",
    "severity": "slight",
    "affects": [
      {
        "vehicle_journeys": [
          "17503"
        ]
      }
    ]
  },
  {
    "situation_number": "QOM:Broadcast::3627054843441640467:LOC",
    "summary": "Weitere Informationen :",
    "description": "",
    "severity": "slight",
    "affects": [
      {
        "vehicle_journeys": [
          "831811"
        ]
      }
    ]
  },
  {
    "situation_number": "QOM:Broadcast::8923947659299250919:LOC",
    "summary": "Weitere Informationen :",
    "description": "",
    "severity": "slight",
    "affects": [
      {
        "vehicle_journeys": [
          "863032"
        ]
      }
    ]
  },
  {
    "situation_number": "QOM:Broadcast::7141093709539596648:LOC",
    "summary": "Geplante Arbeiten zwischen  Roissy CDG und der Picardie und Stadtüberquerung Pleyel St Denis",
    "description": "Arbeiten",
    "severity": "slight",
    "affects": [
      {
        "vehicle_journeys": [
          "847850",
          "847835",
          "847831",
          "847832",
          "847867",
          "847869",
          "847863",
          "847871",
          "847873",
          "847856",
          "847857",
          "847858",
          "847859",
          "847852",
          "847854",
          "847855",
          "847860",
          "847809",
          "847927",
          "847928",
          "847922",
          "847802",
          "847804",
          "847925",
          "847920",
          "16480",
          "847919",
          "16474",
          "16475",
          "16472",
          "16473",
          "16478",
          "847916",
          "847917",
          "847918",
          "16477",
          "847911",
          "847912",
          "847914",
          "847910",
          "16470",
          "16471",
          "16462",
          "847827",
          "16467",
          "16468",
          "847829",
          "16465",
          "16466",
          "847945",
          "847826",
          "847820",
          "847941",
          "847943",
          "16460",
          "16452",
          "16453",
          "16450",
          "16451",
          "847816",
          "16456",
          "16457",
          "847818",
          "847939",
          "16454",
          "16455",
          "847933",
          "847934",
          "847935",
          "847814",
          "16458",
          "16459",
          "847810",
          "847931",
          "847932",
          "847908",
          "16420",
          "847909",
          "16423",
          "847904",
          "847905",
          "16421",
          "847906",
          "16422",
          "847907",
          "847900",
          "847903",
          "847885",
          "847887",
          "847878",
          "847875",
          "847876",
          "847877",
          "847882",
          "847880",
          "439054"
        ]
      }
    ]
  },
  {
    "situation_number": "QOM:Broadcast::1392841479767491535:LOC",
    "summary": "Weitere Informationen :",
    "description": "",
    "severity": "slight",
    "affects": [
      {
        "vehicle_journeys": [
          "88622",
          "88706"
        ]
      }
    ]
  },
  {
    "situation_number": "QOM:Broadcast::1018986219788946765:LOC",
    "summary": "Der Wagen nicht am Bahnsteig",
    "description": "Wir informieren Sie, dass die letzten Wagen dieses Zuges liO nicht am Bahnsteig Der Bahnsteig in den Bahnhöfen GALLARGUES, UCHAUD, MILHAUD und SAINT-CESAIRE empfangen werden.",
    "severity": "slight",
    "affects": [
      {
        "vehicle_journeys": [
          "876302"
        ],
        "stop_points": [
          "87773002",
          "87773457",
          "87773408",
          "87775114",
          "87775130",
          "87775098",
          "87775106",
          "87775072"
        ]
      }
    ]
  },
  {
    "situation_number": "QOM:Broadcast::6882492389165716864:LOC",
    "summary": "Wagen nicht am Bahnsteig",
    "description": "Wir möchten Sie darauf hinweisen, dass die letzten Wagen dieses Zuges nicht am Bahnsteig Der Bahnsteig empfangen werden. .",
    "severity": "slight",
    "affects": [
      {}
    ]
  },
  {
    "situation_number": "QOM:Broadcast::5180567792418978227:LOC",
    "summary": "Perturbation Lorraine.",
    "description": " Lorraine: 5h, la circulation est perturbée entre Thionville et Luxembourg suite à la panne d'un passage à niveau.\n\nPrévision de reprise normale des circulations vers 11h.",
    "severity": "slight",
    "affects": [
      {}
    ]
  },
  {
    "situation_number": "QOM:Broadcast::991173755971782542:LOC",
    "summary": "Laufende Arbeiten.",
    "description": "Vom 23. März bis 10. April wird Ihr Zug montags bis freitags durch einen Bus von Revigny nach Commercy ersetzt.",
    "severity": "slight",
    "affects": [
      {
        "vehicle_journeys": [
          "835647"
        ]
      }
    ]
  },
  {
    "situation_number": "QOM:Broadcast::1490837280554360264:LOC",
    "summary": "Der Wagen nicht am Bahnsteig",
    "description": "Bitte beachten Sie, dass die letzten Wagen dieses Zuges nicht am Bahnsteig Der Bahnsteig von Marquixanes empfangen werden.",
    "severity": "slight",
    "affects": [
      {
        "vehicle_journeys": [
          "877652"
        ],
        "stop_points": [
          "87784686",
          "87784637",
          "87784629",
          "87784660"
        ]
      }
    ]
  },
  {
    "situation_number": "QOM:Broadcast::5359419029301249657:LOC",
    "summary": "Info Arbeiten Frasne Vallorbe",
    "description": "Zwischen Frasne und Vallorbe finden bis zum 19. März, von Montag bis Donnerstag, Bauarbeiten statt. Der Verkehr wird mit Ausfällen angepasst.\n\nEs wird ein Busservice mit einer begrenzten Anzahl an Sitzplätzen eingerichtet.\n\nÜberprüfen Sie Ihre Fahrpläne vor Ihrer Reise.",
    "severity": "slight",
    "affects": [
      {
        "vehicle_journeys": [
          "419528",
          "36529",
          "36531",
          "36532",
          "36533",
          "36536",
          "36538",
          "36539",
          "36540",
          "36541",
          "36542",
          "36543",
          "36544",
          "36545",
          "36546",
          "36547",
          "36551",
          "18146",
          "36553",
          "18142",
          "18140",
          "18136",
          "18134",
          "18133",
          "18138",
          "36569",
          "418515",
          "419606",
          "418512",
          "418511",
          "418514",
          "18130",
          "418513",
          "895709",
          "36573",
          "36574",
          "895708",
          "18122",
          "36576",
          "18129",
          "36577",
          "18128",
          "36570",
          "36572",
          "895701",
          "895702",
          "895705",
          "895703",
          "895704",
          "419627",
          "419624"
        ]
      }
    ]
  },
  {
    "situation_number": "QOM:Broadcast::7306532319994895924:LOC",
    "summary": "Conditions de départ non réunies : Votre TER du 17/03 est supprimé.",
    "description": "Conditions de départ non réunies : Votre TER du 17/03 est supprimé.\n\nDes solutions plus adaptées à votre voyage peuvent être disponibles. Pour cela, rendez-vous sur votre site TER Nouvelle-Aquitaine, sur SNCF Connect ou toute autre application de mobilité.",
    "severity": "slight",
    "affects": [
      {
        "vehicle_journeys": [
          "867261"
        ]
      }
    ]
  },
  {
    "situation_number": "QOM:Broadcast::2336235424930333916:LOC",
    "summary": "Weitere Informationen :",
    "description": "",
    "severity": "slight",
    "affects": [
      {
        "vehicle_journeys": [
          "866449"
        ]
      }
    ]
  },
  {
    "situation_number": "QOM:Broadcast::5772132690927495566:LOC",
    "summary": "Laufende Arbeiten.",
    "description": " Vom 23. März bis 10. April wird Ihr Zug montags bis freitags durch einen Bus von Revigny nach Commercy ersetzt.",
    "severity": "slight",
    "affects": [
      {}
    ]
  },
  {
    "situation_number": "QOM:Broadcast::4532406928899064802:LOC",
    "summary": "Weitere Informationen :",
    "description": "",
    "severity": "slight",
    "affects": [
      {
        "vehicle_journeys": [
          "885100"
        ]
      }
    ]
  },
  {
    "situation_number": "QOM:Broadcast::4954976672471790289:LOC",
    "summary": "Der Wagen nicht am Bahnsteig",
    "description": "Wir möchten Sie darauf hinweisen, dass die letzten Wagen dieses Zuges nicht am Bahnsteig Der Bahnsteig empfangen werden.  .",
    "severity": "slight",
    "affects": [
      {}
    ]
  },
  {
    "situation_number": "QOM:Broadcast::3056519355066741172:LOC",
    "summary": "Conditions de départ non réunies : Votre TER du 17/03 est supprimé.",
    "description": "Conditions de départ non réunies : Votre TER du 17/03 est supprimé.\n\nDes solutions plus adaptées à votre voyage peuvent être disponibles. Pour cela, rendez-vous sur votre site TER Nouvelle-Aquitaine, sur SNCF Connect ou toute autre application de mobilité.",
    "severity": "slight",
    "affects": [
      {
        "vehicle_journeys": [
          "867256"
        ]
      }
    ]
  },
  {
    "situation_number": "QOM:Broadcast::7518117418171712150:LOC",
    "summary": "Argenton-sur-Creuse: Änderung der Verkaufsbedingungen",
    "description": "Argenton-sur-Creuse\n\nDBR HS. Kein Verkauf im Bahnhof außerhalb der Schalteröffnungszeiten möglich.",
    "severity": "slight",
    "affects": [
      {
        "stop_points": [
          "87597120"
        ]
      }
    ]
  },
  {
    "situation_number": "QOM:Broadcast::348251196454204958:LOC",
    "summary": "Weitere Informationen :",
    "description": "",
    "severity": "slight",
    "affects": [
      {
        "vehicle_journeys": [
          "871205"
        ]
      }
    ]
  },
  {
    "situation_number": "QOM:Broadcast::1098356727324876193:LOC",
    "summary": "Travaux en cours sur la ligne 51 .",
    "description": "Travaux en cours sur la ligne 51 .\n\nPlus d'infos sur le site TER Nouvelle-Aquitaine.",
    "severity": "slight",
    "affects": [
      {
        "vehicle_journeys": [
          "455625",
          "455604",
          "866464",
          "866468",
          "866470",
          "866473",
          "866474",
          "866478",
          "866484",
          "866449",
          "866451",
          "866453",
          "866457",
          "866461",
          "866462",
          "866463",
          "866549",
          "866429",
          "866420",
          "866422",
          "866543",
          "866547",
          "866551",
          "866439",
          "866431",
          "866553",
          "866433",
          "866435",
          "866437",
          "866527",
          "866407",
          "866528",
          "866529",
          "866409",
          "866520",
          "866400",
          "866521",
          "866522",
          "866523",
          "866524",
          "866525",
          "866526",
          "866539",
          "866419",
          "866410",
          "866411",
          "866412",
          "866533",
          "866413",
          "866534",
          "866414",
          "866416",
          "866537",
          "866506",
          "866508",
          "866500",
          "866502",
          "866504",
          "866516",
          "866517",
          "866518",
          "866519",
          "866510",
          "866511",
          "866514",
          "455529"
        ]
      }
    ]
  },
  {
    "situation_number": "QOM:Broadcast::5740894725298281652:LOC",
    "summary": "AFFLUENCE3",
    "description": "Ce train circule aujourd'hui avec un nombre réduit de places.",
    "severity": "slight",
    "affects": [
      {
        "vehicle_journeys": [
          "843209",
          "843207",
          "844802",
          "844917"
        ]
      }
    ]
  },
  {
    "situation_number": "QOM:Broadcast::1902479638810482745:LOC",
    "summary": "Ihr Zug hat Verspätung.",
    "description": "Ihr Zug hat Verspätung. \n\nGrund: Technische Überprüfungen am Triebzug in TOULOUSE-MATABIAU .",
    "severity": "slight",
    "affects": [
      {
        "vehicle_journeys": [
          "3750"
        ]
      }
    ]
  },
  {
    "situation_number": "QOM:Broadcast::4441391144879439076:LOC",
    "summary": "Motif de la suppression",
    "description": "de l'absence de certains agents dont la présence est indispensable pour assurer la circulation de votre train",
    "severity": "slight",
    "affects": [
      {
        "vehicle_journeys": [
          "841925",
          "841923"
        ]
      }
    ]
  },
  {
    "situation_number": "QOM:Broadcast::919928998256926295:LOC",
    "summary": "Glissement de terrain provoqué par les intempéries",
    "description": "La circulation est interrompue entre Kalhausen et Sarreguemines au moins jusqu'au vendredi 27 mars, en raison d'un glissement de terrain provoqué par les intempéries.\n\nDes cars de remplacement sont mis en place.\n\nRetrouvez l'info sur vos canaux habituels.",
    "severity": "slight",
    "affects": [
      {
        "vehicle_journeys": [
          "86390",
          "86391",
          "86381",
          "86382",
          "86383",
          "43996",
          "43995",
          "86380",
          "86389",
          "86386",
          "86387",
          "86388",
          "43992",
          "43991",
          "43994",
          "43993",
          "43990",
          "830929",
          "830928",
          "830923",
          "830922",
          "830921",
          "830920",
          "830927",
          "830926",
          "830925",
          "830924",
          "830939",
          "830934",
          "830933",
          "830932",
          "830931",
          "830938",
          "830937",
          "830936",
          "830935",
          "830930",
          "430987",
          "430988",
          "830941",
          "830940",
          "430981",
          "430980",
          "430983",
          "430982",
          "830919",
          "830918",
          "830917",
          "830912",
          "830916",
          "830915",
          "830914",
          "830913",
          "430920",
          "430923",
          "430922",
          "430925",
          "430924",
          "430927",
          "430926",
          "430929",
          "430928",
          "430930",
          "430932",
          "430931",
          "430934",
          "430933",
          "430937",
          "430912",
          "430914",
          "430916",
          "430915",
          "430918",
          "430917",
          "430919"
        ]
      }
    ]
  },
  {
    "situation_number": "QOM:Broadcast::3544572037116430144:LOC",
    "summary": "Anpassung des Verkehrs",
    "description": "Der Verkehr wird angepasst. \n\nUrsache: Vereisung der Oberleitungen, die sich auf den Verkehr Ihres Zuges zwischen PARIS und DIJON auswirkt.",
    "severity": "slight",
    "affects": [
      {
        "vehicle_journeys": [
          "6700",
          "6741",
          "9203",
          "6760"
        ]
      }
    ]
  },
  {
    "situation_number": "QOM:Broadcast::6679025902868330542:LOC",
    "summary": "Weitere Informationen :",
    "description": "",
    "severity": "slight",
    "affects": [
      {
        "vehicle_journeys": [
          "867256"
        ]
      }
    ]
  },
  {
    "situation_number": "QOM:Broadcast::8124907652270617155:LOC",
    "summary": "Weitere Informationen :",
    "description": "",
    "severity": "slight",
    "affects": [
      {
        "vehicle_journeys": [
          "19901"
        ]
      }
    ]
  },
  {
    "situation_number": "QOM:Broadcast::172373343706148186:LOC",
    "summary": "Präzisierungen 17752",
    "description": "Hinweis: Ihr Zug besteht aus folgenden Teilen\n\n2 Züge \n\nmit Abfahrt in MACON. Der vordere Zug hat das Reiseziel PARIS BERCY.\n\nDas Reiseziel des hinteren Zuges ist DIJON.\n\nSeien Sie beim Einsteigen vorsichtig.",
    "severity": "slight",
    "affects": [
      {
        "vehicle_journeys": [
          "17752"
        ]
      }
    ]
  },
  {
    "situation_number": "QOM:Broadcast::6616109756355145109:LOC",
    "summary": "Info confort TER 859405",
    "description": "Votre TER 859405 Ancenis Bis 7h07 Nantes 7h36 circule le 17/03 avec moins de places assises que prévues.",
    "severity": "slight",
    "affects": [
      {
        "vehicle_journeys": [
          "859405"
        ]
      }
    ]
  },
  {
    "situation_number": "QOM:Broadcast::206983811181994358:LOC",
    "summary": "Der Wagen nicht am Bahnsteig",
    "description": "Wir möchten Sie darauf hinweisen, dass die letzten Wagen dieses Zuges nicht am Bahnsteig Der Bahnsteig empfangen werden.  .",
    "severity": "slight",
    "affects": [
      {
        "vehicle_journeys": [
          "849633",
          "849627",
          "849607",
          "849629",
          "849613",
          "849623",
          "849625"
        ],
        "stop_points": [
          "87276774",
          "87276774",
          "87276774",
          "87276774",
          "87276774",
          "87276774",
          "87276774"
        ]
      }
    ]
  },
  {
    "situation_number": "QOM:Broadcast::3501903536013809633:LOC",
    "summary": "Chinon: Änderung der Verkaufsbedingungen",
    "description": "Chinon\n\nDBR HS. Kein Verkauf im Bahnhof außerhalb der Schalteröffnungszeiten möglich.",
    "severity": "slight",
    "affects": [
      {
        "stop_points": [
          "87571687"
        ]
      }
    ]
  },
  {
    "situation_number": "QOM:Broadcast::1230305462348957058:LOC",
    "summary": "Der Zug gelöscht",
    "description": "Ihr Zug wird gelöscht.\n\nGrund: Lokomotive aufgrund von Wartungsarbeiten in PARIS AUSTERLITZ nicht verfügbar.",
    "severity": "slight",
    "affects": [
      {
        "vehicle_journeys": [
          "3789"
        ]
      }
    ]
  },
  {
    "situation_number": "QOM:Broadcast::7021616445808522739:LOC",
    "summary": "Info confort TER 858202",
    "description": "Votre TER 858202 Redon 6h47 Nantes 7h48 circule le 17/03 sans toilettes adaptées aux personnes à mobilité réduite. Nous vous invitons à prendre vos précautions avant le départ du train.",
    "severity": "slight",
    "affects": [
      {
        "vehicle_journeys": [
          "858202"
        ]
      }
    ]
  },
  {
    "situation_number": "QOM:Broadcast::453893542075590452:LOC",
    "summary": "ICV Verspätung 857152",
    "description": "Eine Signalstörung beeinträchtigt den Zugverkehr in der Nähe von La Hutte. Ihr Zug hat Verspätung. Aus Sicherheitsgründen muss der Triebfahrzeugführer die Geschwindigkeit reduzieren.",
    "severity": "slight",
    "affects": [
      {
        "vehicle_journeys": [
          "857152"
        ]
      }
    ]
  },
  {
    "situation_number": "QOM:Broadcast::212910444762620048:LOC",
    "summary": "Laufende Arbeiten.",
    "description": "Vom 23. März bis 10. April wird Ihr Zug montags bis freitags durch einen Bus von Commercy nach Bar-le-Duc ersetzt.",
    "severity": "slight",
    "affects": [
      {
        "vehicle_journeys": [
          "835634",
          "835630"
        ]
      }
    ]
  },
  {
    "situation_number": "QOM:Broadcast::5571090122952944244:LOC",
    "summary": "Saint-Cyr-en-Val: Änderung der Verkaufsbedingungen",
    "description": "Saint-Cyr-en-Val\n\nSchalter den ganzen Tag über geschlossen. Verkauf nur an Terminals möglich.",
    "severity": "slight",
    "affects": [
      {
        "stop_points": [
          "87543116"
        ]
      }
    ]
  },
  {
    "situation_number": "QOM:Broadcast::5877645664845852009:LOC",
    "summary": "Weitere Informationen :",
    "description": "",
    "severity": "slight",
    "affects": [
      {
        "vehicle_journeys": [
          "883503"
        ]
      }
    ]
  },
  {
    "situation_number": "QOM:Broadcast::4217495622523318724:LOC",
    "summary": "Der Wagen nicht am Bahnsteig",
    "description": "Wir möchten Sie darauf hinweisen, dass die letzten Wagen dieses Zuges nicht am Bahnsteig Der Bahnsteig empfangen werden.  .",
    "severity": "slight",
    "affects": [
      {
        "vehicle_journeys": [
          "849606",
          "849628",
          "849608",
          "849610"
        ],
        "stop_points": [
          "87276774",
          "87272195",
          "87276766",
          "87276741",
          "87276774",
          "87272195",
          "87276766",
          "87276741",
          "87276774",
          "87272195",
          "87276766",
          "87276741",
          "87276774",
          "87272195",
          "87276766",
          "87276741"
        ]
      }
    ]
  },
  {
    "situation_number": "QOM:Broadcast::2679876407575425094:LOC",
    "summary": "Travaux en cours sur la ligne 44 .",
    "description": "Travaux en cours sur la ligne 44 .\n\nPlus d'infos sur le site TER Nouvelle-Aquitaine.",
    "severity": "slight",
    "affects": [
      {
        "vehicle_journeys": [
          "866802",
          "866803",
          "866804",
          "866805",
          "866806",
          "866807",
          "866808",
          "866801",
          "866815",
          "866817",
          "866818",
          "866819",
          "866810",
          "866811",
          "866812",
          "453865",
          "453872",
          "453720",
          "866884",
          "866888",
          "866860",
          "866862",
          "866741",
          "866742",
          "866864",
          "866744",
          "866867",
          "866870",
          "453814",
          "453832",
          "866879",
          "71804",
          "866871",
          "866873",
          "866874",
          "866875",
          "866876",
          "866877",
          "866878",
          "866881",
          "453709",
          "866725",
          "866726",
          "866728",
          "866729",
          "866721",
          "866723",
          "866736",
          "866737",
          "866739",
          "866730",
          "866731",
          "866733",
          "866734",
          "866735",
          "453809",
          "866824",
          "866703",
          "866825",
          "866704",
          "866826",
          "866705",
          "866827",
          "866706",
          "866828",
          "866707",
          "866829",
          "866708",
          "866820",
          "866821",
          "866700",
          "866701",
          "866823",
          "866702",
          "866714",
          "866715",
          "866716",
          "866717",
          "866718",
          "866719",
          "866830",
          "866831",
          "866710",
          "866832",
          "866711",
          "866712"
        ]
      }
    ]
  },
  {
    "situation_number": "QOM:Broadcast::1624385924656884354:LOC",
    "summary": "    17.03, La Hutte, Störung der Beschilderung",
    "description": "Langsamer Verkehr in beide Richtungen auf der Strecke Alençon - Le Mans - Château-du-Loir.\n\nStörung der Beschilderung in La Hutte. Unsere technischen Teams sind im Einsatz.\n\nWiederaufnahme des Verkehrs voraussichtlich um 09:00 Uhr.\n\nÜberprüfen Sie Ihre Fahrpläne.",
    "severity": "slight",
    "affects": [
      {
        "vehicle_journeys": [
          "857152",
          "857051",
          "857052",
          "857151",
          "857156",
          "857001",
          "857254",
          "857006",
          "857280"
        ]
      }
    ]
  },
  {
    "situation_number": "QOM:Broadcast::2235992452144631445:LOC",
    "summary": "Ihr Sitzplatz im vorderen Teil des Zuges für Reisende nach Das Reiseziel Beaucaire and Tarascon.",
    "description": "Eine oder mehrere Türen Ihres TER 876404 werden am Bahnsteig in den Bahnhöfen Beaucaire und Tarascon nicht angehalten. Reisende mit Reiseziel Das Reiseziel werden gebeten, in den vorderen Teil des Zuges einzusteigen.",
    "severity": "slight",
    "affects": [
      {
        "vehicle_journeys": [
          "876404"
        ]
      }
    ]
  },
  {
    "situation_number": "QOM:Broadcast::9134031282653493647:LOC",
    "summary": "Weitere Informationen :",
    "description": "",
    "severity": "slight",
    "affects": [
      {
        "vehicle_journeys": [
          "23410"
        ]
      }
    ]
  },
  {
    "situation_number": "QOM:Broadcast::1637245285990557253:LOC",
    "summary": "Weitere Informationen:",
    "description": "",
    "severity": "slight",
    "affects": [
      {
        "vehicle_journeys": [
          "891000"
        ]
      }
    ]
  },
  {
    "situation_number": "QOM:Broadcast::1201280258844944898:LOC",
    "summary": "ICV Verspätung 857280",
    "description": "Eine Signalstörung beeinträchtigt den Zugverkehr in der Nähe von La Hutte. Ihr Zug hat Verspätung. Aus Sicherheitsgründen muss der Triebfahrzeugführer die Geschwindigkeit reduzieren.",
    "severity": "slight",
    "affects": [
      {
        "vehicle_journeys": [
          "857280"
        ]
      }
    ]
  },
  {
    "situation_number": "QOM:Broadcast::3883163746817539173:LOC",
    "summary": "Weitere Informationen :",
    "description": "",
    "severity": "slight",
    "affects": [
      {
        "vehicle_journeys": [
          "886103"
        ]
      }
    ]
  },
  {
    "situation_number": "QOM:Broadcast::4310783155917846039:LOC",
    "summary": "Laufende Arbeiten.",
    "description": "Vom 23. März bis 10. April wird Ihr Zug montags bis freitags durch einen Bus von Commercy nach Bar-le-Duc ersetzt.",
    "severity": "slight",
    "affects": [
      {
        "vehicle_journeys": [
          "835632"
        ]
      }
    ]
  },
  {
    "situation_number": "QOM:Broadcast::5511184450228278212:LOC",
    "summary": "Weitere Informationen:",
    "description": "",
    "severity": "slight",
    "affects": [
      {
        "vehicle_journeys": [
          "891002",
          "891204"
        ]
      }
    ]
  },
  {
    "situation_number": "QOM:Broadcast::7798785227420100509:LOC",
    "summary": "Info confort TER 863702",
    "description": "Votre TER 863702 Bressuire 5h41 Tours 7h43 circule le 17/03 avec moins de places assises que prévues.",
    "severity": "slight",
    "affects": [
      {
        "vehicle_journeys": [
          "863702"
        ]
      }
    ]
  },
  {
    "situation_number": "QOM:Broadcast::2508869963384404033:LOC",
    "summary": "Information Travaux Ligne P20 et K20 du 13 au 17 avril 2026",
    "description": "",
    "severity": "slight",
    "affects": [
      {
        "vehicle_journeys": [
          "849417",
          "849420",
          "848617",
          "849410"
        ]
      }
    ]
  },
  {
    "situation_number": "QOM:Broadcast::4822888902481647871:LOC",
    "summary": "Ihr Sitzplatz im vorderen Teil des Zuges für Reisende mit Reiseziel Saint-Chamas.",
    "description": "Eine oder mehrere Türen Ihres TER ZOU 879653 werden am Bahnsteig im Bahnhof Saint-Chamas nicht angehalten. Reisende mit Reiseziel Das Reiseziel werden gebeten, in den vorderen Teil des Zuges einzusteigen.",
    "severity": "slight",
    "affects": [
      {
        "vehicle_journeys": [
          "879653"
        ]
      }
    ]
  },
  {
    "situation_number": "QOM:Broadcast::1258809677971410110:LOC",
    "summary": "Travaux en cours sur la ligne 16 .",
    "description": "Travaux en cours sur la ligne 16 .\n\nPlus d'infos sur le site TER Nouvelle-Aquitaine.",
    "severity": "slight",
    "affects": [
      {
        "vehicle_journeys": [
          "864502",
          "864623",
          "864501",
          "864622",
          "448536",
          "864626",
          "864625",
          "864504",
          "448540",
          "864512",
          "864510",
          "448544",
          "448546",
          "864518",
          "864516",
          "864514",
          "864324",
          "864562",
          "448513",
          "864328",
          "448509",
          "864337",
          "864336",
          "864335",
          "864333",
          "864331",
          "864330",
          "448527",
          "864546",
          "864544",
          "864540",
          "864548",
          "864556",
          "864554",
          "864552",
          "864550",
          "448505",
          "864558",
          "864560",
          "864522",
          "864520",
          "864529",
          "864525",
          "864532",
          "864530",
          "864536"
        ]
      }
    ]
  },
  {
    "situation_number": "QOM:Broadcast::4935302217123761773:LOC",
    "summary": "Weitere Informationen :",
    "description": "",
    "severity": "slight",
    "affects": [
      {
        "vehicle_journeys": [
          "839561"
        ]
      }
    ]
  },
  {
    "situation_number": "QOM:Broadcast::4768950171922780993:LOC",
    "summary": "Abfahrtbedingungen nicht erfüllt",
    "description": "Da Ihr Zug teilweise gestrichen wurde, finden Sie Ihre Umsteigemöglichkeit mithilfe der Routensuche auf der TER-Website Hauts-de-France, auf SNCF Connect oder in jeder anderen Mobilitätsanwendung.",
    "severity": "slight",
    "affects": [
      {
        "vehicle_journeys": [
          "841925",
          "841923"
        ]
      }
    ]
  },
  {
    "situation_number": "QOM:Broadcast::7644109580912713604:LOC",
    "summary": "Weitere Informationen :",
    "description": "",
    "severity": "slight",
    "affects": [
      {
        "vehicle_journeys": [
          "879724",
          "879735"
        ]
      }
    ]
  },
  {
    "situation_number": "QOM:Broadcast::7195358648307866318:LOC",
    "summary": "Weitere Informationen :",
    "description": "",
    "severity": "slight",
    "affects": [
      {
        "vehicle_journeys": [
          "864623"
        ]
      }
    ]
  },
  {
    "situation_number": "QOM:Broadcast::5729618513493455406:LOC",
    "summary": "BLS et guichet hors service: panne informatique.",
    "description": "A la suite d'une panne informatique nationale, Nous vous informons que les guichets de vente ainsi que les BLS sont exceptionnellement hors service le mercredi 11 mars. \n\nMerci de votre compréhension.",
    "severity": "slight",
    "affects": [
      {}
    ]
  },
  {
    "situation_number": "QOM:Broadcast::3146015716692195257:LOC",
    "summary": "Weitere Informationen :",
    "description": "",
    "severity": "slight",
    "affects": [
      {
        "vehicle_journeys": [
          "831809"
        ]
      }
    ]
  },
  {
    "situation_number": "QOM:Broadcast::2566222138595663379:LOC",
    "summary": "Weitere Informationen :",
    "description": "",
    "severity": "slight",
    "affects": [
      {
        "vehicle_journeys": [
          "877550"
        ]
      }
    ]
  },
  {
    "situation_number": "QOM:Broadcast::3193424347339604473:LOC",
    "summary": "Ausstattung im Bahnhof   : außer Betrieb",
    "description": "Bahnhof  : Die Störung wird in Kauf genommen, wir danken Ihnen für Ihr Verständnis.",
    "severity": "slight",
    "affects": [
      {
        "vehicle_journeys": [
          "43406",
          "841602",
          "841921",
          "43405",
          "841920",
          "841923",
          "43407",
          "841603",
          "841900",
          "841922",
          "43402",
          "841903",
          "841925",
          "43401",
          "841902",
          "841924",
          "43404",
          "841905",
          "43403",
          "841904",
          "841600",
          "439003",
          "841907",
          "841906",
          "43400",
          "841909",
          "841908",
          "841910",
          "841912",
          "841911",
          "841914",
          "841913",
          "841916",
          "841915",
          "439012",
          "841918",
          "841917",
          "841919"
        ]
      }
    ]
  },
  {
    "situation_number": "QOM:Broadcast::5546252565623913696:LOC",
    "summary": "Ihr Zug hat Verspätung",
    "description": "Ihr Zug wird eine andere Route nehmen, um den Baustellenbereich zu umgehen. Daher ist mit einer Verlängerung der Fahrzeit zu rechnen.\n\nUrsache: Unangekündigte Bauarbeiten mit Verlangsamung der Geschwindigkeit des Zuges zwischen HAZEBROUCK und BÉTHUNE.",
    "severity": "slight",
    "affects": [
      {
        "vehicle_journeys": [
          "7520"
        ]
      }
    ]
  },
  {
    "situation_number": "QOM:Broadcast::4032063694194123317:LOC",
    "summary": "Der Wagen nicht am Bahnsteig",
    "description": "Wir informieren Sie, dass die letzten Wagen dieses liO-Zuges nicht am Bahnsteig in den Bahnhöfen VALERGUES und LUNEL-VIEL empfangen werden.",
    "severity": "slight",
    "affects": [
      {
        "vehicle_journeys": [
          "876362"
        ],
        "stop_points": [
          "87773002",
          "87773457",
          "87773432",
          "87773424"
        ]
      }
    ]
  },
  {
    "situation_number": "QOM:Broadcast::3892095105701517277:LOC",
    "summary": "Der Zug gelöscht",
    "description": "Ihr Zug wird gelöscht.\n\nGrund: Materialmangel aufgrund von Wartungsarbeiten in PARIS NORD",
    "severity": "slight",
    "affects": [
      {
        "vehicle_journeys": [
          "63"
        ]
      }
    ]
  },
  {
    "situation_number": "QOM:Broadcast::6226736297579124469:LOC",
    "summary": "Weitere Informationen :",
    "description": "",
    "severity": "slight",
    "affects": [
      {
        "vehicle_journeys": [
          "867261"
        ]
      }
    ]
  },
  {
    "situation_number": "QOM:Broadcast::8428963280156621691:LOC",
    "summary": "Laufende Arbeiten.",
    "description": " Vom 23. März bis 10. April wird Ihr Zug montags bis freitags durch einen Bus von Bar-le-Duc nach Commercy ersetzt.",
    "severity": "slight",
    "affects": [
      {
        "vehicle_journeys": [
          "835635",
          "835637",
          "835633"
        ]
      }
    ]
  },
  {
    "situation_number": "QOM:Broadcast::9083901641864502978:LOC",
    "summary": "Weitere Informationen:",
    "description": "",
    "severity": "slight",
    "affects": [
      {
        "vehicle_journeys": [
          "894602"
        ]
      }
    ]
  },
  {
    "situation_number": "QOM:Broadcast::6626517298351893179:LOC",
    "summary": "Info confort train 859552",
    "description": "Votre train 859552 Nantes 6h10 Nort-sur-Erdre 6h47 du 17/03 circulera avec moins de places assises que prévues. Merci de votre compréhension.",
    "severity": "slight",
    "affects": [
      {
        "vehicle_journeys": [
          "859552"
        ]
      }
    ]
  },
  {
    "situation_number": "QOM:Broadcast::3931663925961940084:LOC",
    "summary": "Travaux en cours sur la ligne 21 .",
    "description": "Travaux en cours sur la ligne 21 .\n\nPlus d'infos sur le site TER Nouvelle-Aquitaine.",
    "severity": "slight",
    "affects": [
      {
        "vehicle_journeys": [
          "451001",
          "869022",
          "869002",
          "869024",
          "869001",
          "869003",
          "869025",
          "869005"
        ]
      }
    ]
  },
  {
    "situation_number": "QOM:Broadcast::4900817698894251483:LOC",
    "summary": "Ihr Zug hat Verspätung.",
    "description": " Ihr Zug hat Verspätung. \n\nGrund: Technische Überprüfungen am Triebzug in NÎMES CENTRE.",
    "severity": "slight",
    "affects": [
      {
        "vehicle_journeys": [
          "4752"
        ]
      }
    ]
  },
  {
    "situation_number": "QOM:Broadcast::801354868628712379:LOC",
    "summary": "TER supprimé.",
    "description": "Difficultés lors de la préparation du train - 883503  : Votre train ne circulera pas le 17 mars.",
    "severity": "slight",
    "affects": [
      {
        "vehicle_journeys": [
          "883503"
        ]
      }
    ]
  },
  {
    "situation_number": "QOM:Broadcast::7281569959024105543:LOC",
    "summary": "Größere Bauarbeiten mit Auswirkungen auf den Verkehr der TGV INOUI und LYRIA von Februar bis Juni 2026",
    "description": "",
    "severity": "slight",
    "affects": [
      {}
    ]
  },
  {
    "situation_number": "QOM:Broadcast::9074247167064209030:LOC",
    "summary": "Der Wagen nicht am Bahnsteig",
    "description": "Bitte beachten Sie, dass die letzten Wagen dieses Zuges nicht am Bahnsteig Der Bahnsteig von Marquixanes empfangen werden.",
    "severity": "slight",
    "affects": [
      {
        "vehicle_journeys": [
          "877663"
        ],
        "stop_points": [
          "87784546",
          "87784629",
          "87784561",
          "87784009",
          "87784611",
          "87784520",
          "87784512"
        ]
      }
    ]
  },
  {
    "situation_number": "QOM:Broadcast::8309648616549977763:LOC",
    "summary": "Der Wagen nicht am Bahnsteig",
    "description": "Wir informieren Sie, dass die letzten Wagen dieses liO-Zuges nicht am Bahnsteig des/der Bahnhöfe(s) LUNEL-VIEL und VALERGUES empfangen werden.",
    "severity": "slight",
    "affects": [
      {
        "vehicle_journeys": [
          "876337"
        ],
        "stop_points": [
          "87773408",
          "87773432"
        ]
      }
    ]
  },
  {
    "situation_number": "QOM:Broadcast::2877796462784484678:LOC",
    "summary": "Informations",
    "description": " Certains DBR n'acceptent plus les cartes bancaires pour le moment.\n\nPlus d'informations sur le site TER AURA ou l'application SNCF CONNECT.\n\nMerci de votre compréhension.",
    "severity": "slight",
    "affects": [
      {
        "vehicle_journeys": [
          "873619",
          "461203",
          "31120",
          "875730",
          "31206",
          "31306",
          "873357",
          "31127",
          "873351",
          "873352",
          "873991",
          "873353",
          "873771",
          "873656",
          "31332",
          "873050",
          "31196",
          "31471",
          "873200",
          "873123",
          "873662",
          "873102",
          "875700",
          "873400",
          "873262",
          "871201",
          "873264",
          "873660",
          "31335",
          "873221",
          "873364",
          "873100",
          "873769",
          "871203",
          "871202",
          "873721",
          "875702",
          "873767",
          "873702"
        ]
      }
    ]
  },
  {
    "situation_number": "QOM:Broadcast::4355084612778331604:LOC",
    "summary": "Weitere Informationen :",
    "description": "",
    "severity": "slight",
    "affects": [
      {
        "vehicle_journeys": [
          "857302",
          "857702"
        ]
      }
    ]
  },
  {
    "situation_number": "QOM:Broadcast::5824799977255980910:LOC",
    "summary": "Der Zug gelöscht",
    "description": "Ihr Zug wird gelöscht.\n\nGrund: Materialmangel aufgrund von Wartungsarbeiten in RODEZ.",
    "severity": "slight",
    "affects": [
      {
        "vehicle_journeys": [
          "3754"
        ]
      }
    ]
  },
  {
    "situation_number": "QOM:Broadcast::1006270709996396137:LOC",
    "summary": "Ihr Zug hat Verspätung",
    "description": "Ihr Zug hat Verspätung.\n\nUrsache: Verspätete Züge auf demselben Gleis, die den Verkehr zwischen BORDEAUX-ST-JEAN und FACTURE-BIGANOS  überlasten.",
    "severity": "slight",
    "affects": [
      {
        "vehicle_journeys": [
          "3731"
        ]
      }
    ]
  },
  {
    "situation_number": "QOM:Broadcast::2624051260364177205:LOC",
    "summary": "Info confort train 859553",
    "description": "Votre train 859553 Nort-sur-Erdre 7h28 Nantes 8h05 du 17/03 circulera avec moins de places assises que prévues. Merci de votre compréhension.",
    "severity": "slight",
    "affects": [
      {
        "vehicle_journeys": [
          "859553"
        ]
      }
    ]
  },
  {
    "situation_number": "QOM:Broadcast::2947335432436755095:LOC",
    "summary": "Fahrradreservierung erforderlich",
    "description": "Die Fahrradreservierung ist vom 10/06 bis zum 30/04/2026 obligatorisch.",
    "severity": "slight",
    "affects": [
      {
        "vehicle_journeys": [
          "3395",
          "3393",
          "3191",
          "3190",
          "87144",
          "87143",
          "16540",
          "16544",
          "16546",
          "16547",
          "16521",
          "16526",
          "3407",
          "3405",
          "3403",
          "3401",
          "3402",
          "3429",
          "3308",
          "3309",
          "3427",
          "3306",
          "3428",
          "3307",
          "3425",
          "3304",
          "3426",
          "3305",
          "3302",
          "3424",
          "3303",
          "3421",
          "3301",
          "3420",
          "3416",
          "3414",
          "3410",
          "3411",
          "3328",
          "3329",
          "3447",
          "3326",
          "3448",
          "3327",
          "3324",
          "3325",
          "3322",
          "3323",
          "3441",
          "3320",
          "3442",
          "3321",
          "3440",
          "3319",
          "3317",
          "3318",
          "3436",
          "3315",
          "3316",
          "3313",
          "3435",
          "3314",
          "3311",
          "3312",
          "3430",
          "3310",
          "3108",
          "3109",
          "3348",
          "3106",
          "3469",
          "3349",
          "3107",
          "3346",
          "3104",
          "3467",
          "3347",
          "3105",
          "3344",
          "3102",
          "3345",
          "3103",
          "3342",
          "3100",
          "3343",
          "3101",
          "3464",
          "3340",
          "3341",
          "3462",
          "48001",
          "3339",
          "3337",
          "3338",
          "3459",
          "3335",
          "3336",
          "3457",
          "3333",
          "3334",
          "3331",
          "3453",
          "3330",
          "3451",
          "48002",
          "3128",
          "3129",
          "3126",
          "3127",
          "3124",
          "3125",
          "3122",
          "3123",
          "3120",
          "3483",
          "3121",
          "3361",
          "3119",
          "3359",
          "3117",
          "3118",
          "3357",
          "3115",
          "3116",
          "3479",
          "3355",
          "3113",
          "3114",
          "3353",
          "3111",
          "3354",
          "3351",
          "3472",
          "3352",
          "3110",
          "3350",
          "3391",
          "3388",
          "3389",
          "3386",
          "3387",
          "3384",
          "3385",
          "3382",
          "3383",
          "3380",
          "3381",
          "3379",
          "3377",
          "3135",
          "3378",
          "3136",
          "3375",
          "3133",
          "3376",
          "3134",
          "3373",
          "3131",
          "3374",
          "3132",
          "3371",
          "3372",
          "3130"
        ]
      }
    ]
  },
  {
    "situation_number": "QOM:Broadcast::831240601988982065:LOC",
    "summary": "Bauarbeiten zwischen Paris und Crépy-en-Valois geplant",
    "description": "Geplante Arbeiten",
    "severity": "slight",
    "affects": [
      {
        "vehicle_journeys": [
          "849907",
          "849909",
          "849908",
          "849903",
          "849902",
          "849900",
          "849928",
          "849925",
          "849927",
          "849921",
          "849923",
          "849922",
          "849930",
          "849918",
          "849917",
          "849913",
          "849916",
          "849915",
          "849912",
          "849911",
          "849946",
          "849944",
          "849950",
          "849951",
          "849939",
          "849936",
          "849935",
          "849938",
          "849937",
          "849931",
          "849934",
          "849940",
          "849965",
          "849966",
          "849961",
          "849962"
        ]
      }
    ]
  },
  {
    "situation_number": "QOM:Broadcast::6403196361764812921:LOC",
    "summary": "AFFLUENCE3",
    "description": "Der Zug verkehrt heute mit einer geringeren Anzahl an Sitzplätzen.",
    "severity": "slight",
    "affects": [
      {
        "vehicle_journeys": [
          "849908"
        ]
      }
    ]
  },
  {
    "situation_number": "QOM:Broadcast::5100928874450324176:LOC",
    "summary": "Der Zug gelöscht",
    "description": "Ihr Zug wird gelöscht.\n\nGrund: Lokomotive aufgrund von Wartungsarbeiten in AURILLAC nicht verfügbar.",
    "severity": "slight",
    "affects": [
      {
        "vehicle_journeys": [
          "3790"
        ]
      }
    ]
  },
  {
    "situation_number": "QOM:Broadcast::8318071273002874980:LOC",
    "summary": "Informations",
    "description": " A CLERMONT FD , certains DBR n'acceptent plus les cartes bancaires pour le moment.\n\nPlus d'informations sur le site TER AURA ou l'application SNCF CONNECT.\n\nMerci de votre compréhension.",
    "severity": "slight",
    "affects": [
      {
        "vehicle_journeys": [
          "873619",
          "461203",
          "31120",
          "875730",
          "31206",
          "31306",
          "873357",
          "31127",
          "873352",
          "873991",
          "873353",
          "873771",
          "873656",
          "31332",
          "873050",
          "31196",
          "31471",
          "873200",
          "873123",
          "873662",
          "873102",
          "875700",
          "873400",
          "873262",
          "871201",
          "873264",
          "873660",
          "31335",
          "873221",
          "873364",
          "873100",
          "873901",
          "873769",
          "871203",
          "871202",
          "873721",
          "875702",
          "873767",
          "873702"
        ]
      }
    ]
  },
  {
    "situation_number": "QOM:Broadcast::1258454907208759281:LOC",
    "summary": "Distributeur de billet hors service à Châlons-en-Champagne Marne.",
    "description": "Le distributeur de billet est hors service dans la gare de Châlons-en-Champagne Marne.\n\nAchetez votre billet sur l'application SNCF ou ter.sncf.com/grand-est, à défaut merci de vous rapprocher du contrôleur.",
    "severity": "slight",
    "affects": [
      {
        "stop_points": [
          "87742221"
        ]
      }
    ]
  },
  {
    "situation_number": "QOM:Broadcast::3903690637711969264:LOC",
    "summary": "Travaux en cours sur la ligne 18 .",
    "description": "Travaux en cours sur la ligne 18 .\n\nPlus d'infos sur le site TER Nouvelle-Aquitaine.",
    "severity": "slight",
    "affects": [
      {
        "vehicle_journeys": [
          "868104",
          "868103",
          "868106",
          "868105",
          "868108",
          "868107",
          "868109",
          "868111",
          "868110",
          "868113",
          "868112",
          "868114",
          "868116",
          "450109",
          "450108",
          "450107",
          "450106",
          "868140",
          "868142",
          "868141",
          "868144",
          "868143",
          "868102",
          "868101",
          "868145"
        ]
      }
    ]
  },
  {
    "situation_number": "QOM:Broadcast::2612019819617992990:LOC",
    "summary": "ICV Verspätung 858802",
    "description": "Der Zug ist nicht vollständig besetzt, um eine pünktliche Abfahrtszeit zu gewährleisten, er beendet seine Aufgabe auf einer vorherigen Strecke, die derzeit Verspätung hat.",
    "severity": "slight",
    "affects": [
      {
        "vehicle_journeys": [
          "858802"
        ]
      }
    ]
  },
  {
    "situation_number": "QOM:Broadcast::8780246801809087972:LOC",
    "summary": "Weitere Informationen :",
    "description": "",
    "severity": "slight",
    "affects": [
      {
        "vehicle_journeys": [
          "88501",
          "88710",
          "88702",
          "88713",
          "88801",
          "88712",
          "88620",
          "88708",
          "88709",
          "88704",
          "88715",
          "88803",
          "88703",
          "88714",
          "88802",
          "88705",
          "88804"
        ]
      }
    ]
  },
  {
    "situation_number": "QOM:Broadcast::2497365750529440242:LOC",
    "summary": "Wagen am Bahnsteig im Bahnhof Courville",
    "description": "Bei diesem Zug besteht die Gefahr, dass im Bahnhof Courville-sur-Eure Türen über den Bahnsteig hinausragen. Reisende, die in diesem Bahnhof aussteigen, werden gebeten, sich zum vorderen Teil des Zuges zu begeben.",
    "severity": "slight",
    "affects": [
      {
        "vehicle_journeys": [
          "862529"
        ]
      }
    ]
  },
  {
    "situation_number": "QOM:Broadcast::4187117833147998516:LOC",
    "summary": "Train court.",
    "description": " \n\nVotre train sera un train court. Nous faisons tout pour rétablir cette situation.",
    "severity": "slight",
    "affects": [
      {
        "vehicle_journeys": [
          "884672",
          "23117",
          "23239",
          "23338",
          "23138",
          "23312",
          "23133",
          "23155",
          "23332",
          "23254",
          "884558",
          "884613",
          "23231",
          "23154",
          "23350",
          "23328",
          "884682",
          "23425",
          "23424",
          "23149",
          "23368",
          "884620",
          "23146",
          "23466",
          "23488",
          "884684",
          "23420",
          "884625",
          "23242",
          "884700",
          "884501",
          "23141",
          "23382",
          "23419"
        ]
      }
    ]
  },
  {
    "situation_number": "QOM:Broadcast::6249000291434307371:LOC",
    "summary": "Montigny-en-Ostrevent",
    "description": " Montigny-en-Ostrevent : le guichet de la gare est fermé à la vente le mardi 17 mars. Votre titre de transport est disponible à l'achat en avance sur le site TER Hauts de France ou sur vos canaux de distribution habituels.",
    "severity": "slight",
    "affects": [
      {
        "vehicle_journeys": [
          "843506",
          "843804",
          "843504",
          "843802",
          "843868",
          "843808",
          "843508",
          "843806",
          "843564",
          "843862",
          "843562",
          "843860",
          "843502",
          "843524",
          "843568",
          "843800",
          "843866",
          "843500",
          "843522",
          "843566",
          "843820",
          "843864",
          "843550",
          "843570",
          "843814",
          "843858",
          "843518",
          "843812",
          "843856",
          "843516",
          "843818",
          "843816",
          "843850",
          "843510",
          "843554",
          "843870",
          "843552",
          "843750",
          "843810",
          "843854",
          "843514",
          "843558",
          "843852",
          "843512",
          "843556",
          "843560",
          "46564"
        ]
      }
    ]
  },
  {
    "situation_number": "QOM:Broadcast::6297970425715479787:LOC",
    "summary": "    17.03, La Hutte, Störung der Beschilderung",
    "description": "Langsamer Verkehr in beide Richtungen auf der Strecke Alençon - Le Mans - Château-du-Loir...\n\nStörung der Beschilderung in La Hutte. Unsere technischen Teams sind im Einsatz...\n\nWiederaufnahme des Verkehrs voraussichtlich um 09:00 Uhr.\n\nÜberprüfen Sie Ihre Fahrpläne.",
    "severity": "slight",
    "affects": [
      {
        "vehicle_journeys": [
          "857152",
          "857051",
          "857052",
          "857151",
          "857156",
          "857001",
          "857254",
          "857006",
          "857280"
        ]
      }
    ]
  },
  {
    "situation_number": "QOM:Broadcast::7794169976482831869:LOC",
    "summary": "Perturbation en Lorraine.",
    "description": "Lorraine: 5h, la circulation est perturbée entre Thionville et Luxembourg \n\nsuite à la panne d'un passage à niveau.\n\nDes retards et des suppressions sont à prévoir. \n\nNous estimons une reprise des circulations vers 11h.",
    "severity": "slight",
    "affects": [
      {
        "vehicle_journeys": [
          "88770",
          "837683",
          "88710",
          "88713",
          "88712",
          "88730",
          "88708",
          "88806",
          "88809",
          "88709",
          "88726",
          "88704",
          "88803",
          "88703",
          "88725",
          "88802",
          "88706",
          "88805",
          "88705",
          "88804",
          "88700",
          "88722",
          "88721",
          "88702",
          "88724",
          "88801",
          "88701",
          "88719",
          "88718",
          "88715",
          "88714",
          "88717",
          "88716"
        ]
      }
    ]
  },
  {
    "situation_number": "QOM:Broadcast::1126157884337072881:LOC",
    "summary": "Geschlossener Zug für Reisende am Hinten Ihres TER 876433, Zugang über die Vorderseite des Zuges",
    "description": "Der Zug am Hinten Ihres TER 876433 ist geschlossen, der Zugang erfolgt über den vorderen Teil des Zuges.",
    "severity": "slight",
    "affects": [
      {
        "vehicle_journeys": [
          "876433"
        ]
      }
    ]
  },
  {
    "situation_number": "QOM:Broadcast::4025575013749145229:LOC",
    "summary": "Weitere Informationen :",
    "description": "",
    "severity": "slight",
    "affects": [
      {
        "vehicle_journeys": [
          "843650"
        ]
      }
    ]
  },
  {
    "situation_number": "QOM:Broadcast::1944969560835805968:LOC",
    "summary": "Größere Bauarbeiten mit Auswirkungen auf den Verkehr der TGV Atlantique zwischen Januar und Dezember 2026",
    "description": "",
    "severity": "slight",
    "affects": [
      {}
    ]
  },
  {
    "situation_number": "QOM:Broadcast::8492391575133145352:LOC",
    "summary": "Porte hors quai au train 861421 ou élément fermé au service commercial.",
    "description": "Les voyageurs sont invités à monter dans l'élément de tête, ouvert au service commercial.",
    "severity": "slight",
    "affects": [
      {
        "vehicle_journeys": [
          "861421"
        ]
      }
    ]
  },
  {
    "situation_number": "QOM:Broadcast::1493003893958698801:LOC",
    "summary": "Der Wagen nicht am Bahnsteig",
    "description": "Wir informieren Sie, dass die letzten Wagen dieses liO-Zuges nicht am Bahnsteig in den Bahnhöfen von SAINT-AUNES, VALERGUES, LUNEL-VIEL, MILHAUD und SAINT-CESAIRE empfangen werden.",
    "severity": "slight",
    "affects": [
      {
        "vehicle_journeys": [
          "876366"
        ],
        "stop_points": [
          "87773408",
          "87775114",
          "87775072",
          "87775098"
        ]
      }
    ]
  },
  {
    "situation_number": "QOM:Broadcast::9081373084821496222:LOC",
    "summary": "Der Wagen nicht am Bahnsteig",
    "description": "Wir möchten Sie darauf hinweisen, dass die letzten Wagen dieses Zuges nicht am Bahnsteig Der Bahnsteig empfangen werden.  .",
    "severity": "slight",
    "affects": [
      {
        "vehicle_journeys": [
          "848506",
          "848529",
          "848525"
        ],
        "stop_points": [
          "87276212",
          "87313221",
          "87313270",
          "87313304",
          "87313247",
          "87276212",
          "87313221",
          "87313270",
          "87313304",
          "87313247",
          "87276212",
          "87313221",
          "87313270",
          "87313304",
          "87313247"
        ]
      }
    ]
  },
  {
    "situation_number": "QOM:Broadcast::579090921132918864:LOC",
    "summary": "TER supprimé.",
    "description": "Le TER 88706 origine Metz départ à 6h03 à destination de Luxembourg est supprimé.\n\nMerci d'emprunter le TER 88708 départ à 6h07.",
    "severity": "slight",
    "affects": [
      {
        "vehicle_journeys": [
          "88706"
        ]
      }
    ]
  },
  {
    "situation_number": "QOM:Broadcast::8559083495006405804:LOC",
    "summary": "Arbeiten mit Auswirkungen auf den Verkehr des TGV Nord",
    "description": "",
    "severity": "slight",
    "affects": [
      {}
    ]
  },
  {
    "situation_number": "QOM:Broadcast::3218581661423119673:LOC",
    "summary": "Ihr Zug hat Verspätung",
    "description": " \n\n \n\nIhr Zug hat eine Verspätung.\n\nGrund: Unangekündigte Arbeiten mit Verlangsamung der Geschwindigkeit des Zuges zwischen HAZEBROUCK und BÉTHUNE.",
    "severity": "slight",
    "affects": [
      {
        "vehicle_journeys": [
          "7320"
        ]
      }
    ]
  },
  {
    "situation_number": "QOM:Broadcast::7577078446110324676:LOC",
    "summary": "Limitation du parcours du train.",
    "description": "Le TER 88622 est supprimé de Luxembourg à Metz.\n\nMerci d'emprunter le TER 88713 au départ de Luxembourg à 7h39.",
    "severity": "slight",
    "affects": [
      {
        "vehicle_journeys": [
          "88622"
        ]
      }
    ]
  },
  {
    "situation_number": "QOM:Broadcast::3945943229050458024:LOC",
    "summary": "Ihr Zug hat Verspätung",
    "description": "Ihr Zug hat eine Verspätung.\n\nGrund: Wartungsarbeiten, die zwischen AIX-EN-PROVENCE-TGV und AVIGNON-TGV später als geplant abgeschlossen wurden.",
    "severity": "slight",
    "affects": [
      {
        "vehicle_journeys": [
          "6102"
        ]
      }
    ]
  },
  {
    "situation_number": "QOM:Broadcast::7779997093933977211:LOC",
    "summary": "Laufende Arbeiten.",
    "description": " Vom 23. März bis 10. April wird Ihr Zug montags bis freitags durch einen Bus von Revigny nach Commercy ersetzt.",
    "severity": "slight",
    "affects": [
      {
        "vehicle_journeys": [
          "433606",
          "433604",
          "833608",
          "833609",
          "833604",
          "833606",
          "833607",
          "833602",
          "833615",
          "833616",
          "833617",
          "833618",
          "833612",
          "434632",
          "833613",
          "434630",
          "434637",
          "434634",
          "833627",
          "833629",
          "434647",
          "833621",
          "433639",
          "434606",
          "433637",
          "433647",
          "433646",
          "433645",
          "433533",
          "433532",
          "433535",
          "433632",
          "433630",
          "433635",
          "433634",
          "433513",
          "433633",
          "835630",
          "835629",
          "835624",
          "835623",
          "835639",
          "835636",
          "835635",
          "835637",
          "835632",
          "835650",
          "835652",
          "835647",
          "835649",
          "835648",
          "835644",
          "45148",
          "833648",
          "833647",
          "833642",
          "833661",
          "833662",
          "835660",
          "835654",
          "835656",
          "835669",
          "835668",
          "835665",
          "835667",
          "835675"
        ]
      }
    ]
  }
]